{
    "data":[
        {
      "id": 1,
      "lat": 26.506299,
      "vehicle_card": "\u8d35AT0652",
      "lng": 106.669967
    },
    {
      "id": 1,
      "lat": 26.733655,
      "vehicle_card": "\u8d35AU4569",
      "lng": 106.687096
    },
    {
      "id": 1,
      "lat": 26.438527,
      "vehicle_card": "\u8d35A964G2",
      "lng": 106.70955
    },
    {
      "id": 1,
      "lat": 26.935948,
      "vehicle_card": "\u8d35A64874",
      "lng": 106.696029
    },
    {
      "id": 1,
      "lat": 26.466935,
      "vehicle_card": "\u8d35AA7987",
      "lng": 106.684506
    },
    {
      "id": 1,
      "lat": 26.536551,
      "vehicle_card": "\u8d35AT1846",
      "lng": 106.788143
    },
    {
      "id": 1,
      "lat": 26.732326,
      "vehicle_card": "\u8d35A01384",
      "lng": 106.690005
    },
    {
      "id": 1,
      "lat": 26.597814,
      "vehicle_card": "\u8d35A37315",
      "lng": 106.577133
    },
    {
      "id": 1,
      "lat": 26.668126,
      "vehicle_card": "\u8d35AU4196",
      "lng": 106.62076
    },
    {
      "id": 1,
      "lat": 26.864328,
      "vehicle_card": "\u8d35A82929",
      "lng": 106.743004
    },
    {
      "id": 1,
      "lat": 26.535144,
      "vehicle_card": "\u8d35A52353",
      "lng": 106.450527
    },
    {
      "id": 1,
      "lat": 27.06643,
      "vehicle_card": "\u8d35AU9938",
      "lng": 106.953271
    },
    {
      "id": 1,
      "lat": 26.604057,
      "vehicle_card": "\u8d35A41057",
      "lng": 106.37857
    },
    {
      "id": 1,
      "lat": 26.598919,
      "vehicle_card": "\u8d35A41781",
      "lng": 106.577815
    },
    {
      "id": 1,
      "lat": 26.55784,
      "vehicle_card": "\u8d35A78189",
      "lng": 106.472266
    },
    {
      "id": 1,
      "lat": 26.65733,
      "vehicle_card": "\u8d35A28821",
      "lng": 106.60745
    },
    {
      "id": 1,
      "lat": 26.440166,
      "vehicle_card": "\u8d35AU3266",
      "lng": 106.674064
    },
    {
      "id": 1,
      "lat": 26.730211,
      "vehicle_card": "\u8d35A41789",
      "lng": 106.360907
    },
    {
      "id": 1,
      "lat": 26.635722,
      "vehicle_card": "\u8d35A38737",
      "lng": 106.356835
    },
    {
      "id": 1,
      "lat": 26.562798,
      "vehicle_card": "\u8d35A38757",
      "lng": 106.447739
    },
    {
      "id": 1,
      "lat": 26.657381,
      "vehicle_card": "\u8d35AT1503",
      "lng": 106.621368
    },
    {
      "id": 1,
      "lat": 26.843968,
      "vehicle_card": "\u8d35A65625",
      "lng": 106.59785
    },
    {
      "id": 1,
      "lat": 26.586316,
      "vehicle_card": "\u8d35A41017",
      "lng": 106.59429
    },
    {
      "id": 1,
      "lat": 26.638071,
      "vehicle_card": "\u8d35A41051",
      "lng": 106.355312
    },
    {
      "id": 1,
      "lat": 26.552849,
      "vehicle_card": "\u8d35A88418",
      "lng": 106.611199
    },
    {
      "id": 1,
      "lat": 26.59955,
      "vehicle_card": "\u8d35A38711",
      "lng": 106.577282
    },
    {
      "id": 1,
      "lat": 26.615848,
      "vehicle_card": "\u8d35AU3890",
      "lng": 106.725718
    },
    {
      "id": 1,
      "lat": 26.948179,
      "vehicle_card": "\u8d35A51059",
      "lng": 106.467671
    },
    {
      "id": 1,
      "lat": 27.06653,
      "vehicle_card": "\u8d35AUA049",
      "lng": 106.956482
    },
    {
      "id": 1,
      "lat": 26.584923,
      "vehicle_card": "\u8d35AU9829",
      "lng": 106.688081
    },
    {
      "id": 1,
      "lat": 26.935789,
      "vehicle_card": "\u8d35A81878",
      "lng": 106.696092
    },
    {
      "id": 1,
      "lat": 26.626417,
      "vehicle_card": "\u8d35AU6606",
      "lng": 106.778706
    },
    {
      "id": 1,
      "lat": 26.630916,
      "vehicle_card": "\u8d35AU5386",
      "lng": 106.739341
    },
    {
      "id": 1,
      "lat": 26.597375,
      "vehicle_card": "\u8d35A51838",
      "lng": 106.57609
    },
    {
      "id": 1,
      "lat": 27.130868,
      "vehicle_card": "\u8d35A35294",
      "lng": 106.864013
    },
    {
      "id": 1,
      "lat": 27.137514,
      "vehicle_card": "\u8d35AU9876",
      "lng": 106.913942
    },
    {
      "id": 1,
      "lat": 26.550493,
      "vehicle_card": "\u8d35AT2292",
      "lng": 106.796066
    },
    {
      "id": 1,
      "lat": 26.639459,
      "vehicle_card": "\u8d35A83198",
      "lng": 106.778396
    },
    {
      "id": 1,
      "lat": 27.062154,
      "vehicle_card": "\u8d35AUB249",
      "lng": 106.958643
    },
    {
      "id": 1,
      "lat": 27.108303,
      "vehicle_card": "\u8d35A72869",
      "lng": 106.729265
    },
    {
      "id": 1,
      "lat": 26.559375,
      "vehicle_card": "\u8d35A77582",
      "lng": 106.482228
    },
    {
      "id": 1,
      "lat": 26.59948,
      "vehicle_card": "\u8d35A43306",
      "lng": 106.578141
    },
    {
      "id": 1,
      "lat": 26.603716,
      "vehicle_card": "\u8d35AT0881",
      "lng": 106.604643
    },
    {
      "id": 1,
      "lat": 27.064593,
      "vehicle_card": "\u8d35AUB928",
      "lng": 106.95556
    },
    {
      "id": 1,
      "lat": 27.06428,
      "vehicle_card": "\u8d35A47328",
      "lng": 106.943863
    },
    {
      "id": 1,
      "lat": 26.724574,
      "vehicle_card": "\u8d35AU4191",
      "lng": 106.623815
    },
    {
      "id": 1,
      "lat": 26.623707,
      "vehicle_card": "\u8d35AT0408",
      "lng": 106.660821
    },
    {
      "id": 1,
      "lat": 27.065106,
      "vehicle_card": "\u8d35AUB298",
      "lng": 106.965633
    },
    {
      "id": 1,
      "lat": 26.652528,
      "vehicle_card": "\u8d35A77566",
      "lng": 106.581481
    },
    {
      "id": 1,
      "lat": 27.06165,
      "vehicle_card": "\u8d35AU9881",
      "lng": 106.966833
    },
    {
      "id": 1,
      "lat": 26.563018,
      "vehicle_card": "\u8d35A65021",
      "lng": 106.475802
    },
    {
      "id": 1,
      "lat": 26.554063,
      "vehicle_card": "\u8d35A56779",
      "lng": 106.45983
    },
    {
      "id": 1,
      "lat": 27.057789,
      "vehicle_card": "\u8d35AUB648",
      "lng": 106.958445
    },
    {
      "id": 1,
      "lat": 27.062742,
      "vehicle_card": "\u8d35AUA925",
      "lng": 106.958019
    },
    {
      "id": 1,
      "lat": 26.564835,
      "vehicle_card": "\u8d35A48615",
      "lng": 106.473304
    },
    {
      "id": 1,
      "lat": 26.725998,
      "vehicle_card": "\u8d35A72293",
      "lng": 106.690425
    },
    {
      "id": 1,
      "lat": 27.065981,
      "vehicle_card": "\u8d35A83270",
      "lng": 106.964408
    },
    {
      "id": 1,
      "lat": 26.523313,
      "vehicle_card": "\u8d35A01116",
      "lng": 106.772111
    },
    {
      "id": 1,
      "lat": 26.578955,
      "vehicle_card": "\u8d35A72290",
      "lng": 106.694675
    },
    {
      "id": 1,
      "lat": 26.598871,
      "vehicle_card": "\u8d35A01268",
      "lng": 106.576416
    },
    {
      "id": 1,
      "lat": 26.63843,
      "vehicle_card": "\u8d35AU6655",
      "lng": 106.771205
    },
    {
      "id": 1,
      "lat": 26.598485,
      "vehicle_card": "\u8d35A01068",
      "lng": 106.576034
    },
    {
      "id": 1,
      "lat": 26.599456,
      "vehicle_card": "\u8d35AU4162",
      "lng": 106.577461
    },
    {
      "id": 1,
      "lat": 26.639035,
      "vehicle_card": "\u8d35AU8182",
      "lng": 106.772067
    },
    {
      "id": 1,
      "lat": 26.595866,
      "vehicle_card": "\u8d35A68965",
      "lng": 106.583578
    },
    {
      "id": 1,
      "lat": 26.561032,
      "vehicle_card": "\u8d35A41033",
      "lng": 106.447901
    },
    {
      "id": 1,
      "lat": 26.623989,
      "vehicle_card": "\u8d35A49519",
      "lng": 106.618682
    },
    {
      "id": 1,
      "lat": 26.598918,
      "vehicle_card": "\u8d35A78287",
      "lng": 106.576526
    },
    {
      "id": 1,
      "lat": 27.061501,
      "vehicle_card": "\u8d35AUB682",
      "lng": 106.956853
    },
    {
      "id": 1,
      "lat": 26.597385,
      "vehicle_card": "\u8d35A01247",
      "lng": 106.57637
    },
    {
      "id": 1,
      "lat": 26.880298,
      "vehicle_card": "\u8d35A57393",
      "lng": 107.104873
    },
    {
      "id": 1,
      "lat": 27.065736,
      "vehicle_card": "\u8d35A72861",
      "lng": 106.631846
    },
    {
      "id": 1,
      "lat": 27.067268,
      "vehicle_card": "\u8d35A54869",
      "lng": 106.867275
    },
    {
      "id": 1,
      "lat": 26.613475,
      "vehicle_card": "\u8d35AA2536",
      "lng": 106.716703
    },
    {
      "id": 1,
      "lat": 26.506184,
      "vehicle_card": "\u8d35AT0712",
      "lng": 106.670047
    },
    {
      "id": 1,
      "lat": 26.483133,
      "vehicle_card": "\u8d35A51744",
      "lng": 106.73588
    },
    {
      "id": 1,
      "lat": 26.593453,
      "vehicle_card": "\u8d35AU5390",
      "lng": 106.696785
    },
    {
      "id": 1,
      "lat": 26.525846,
      "vehicle_card": "\u8d35A29846",
      "lng": 106.772591
    },
    {
      "id": 1,
      "lat": 26.601488,
      "vehicle_card": "\u8d35A61588",
      "lng": 106.581283
    },
    {
      "id": 1,
      "lat": 26.553708,
      "vehicle_card": "\u8d35A41089",
      "lng": 106.478086
    },
    {
      "id": 1,
      "lat": 26.577337,
      "vehicle_card": "\u8d35A58321",
      "lng": 106.556239
    },
    {
      "id": 1,
      "lat": 27.066656,
      "vehicle_card": "\u8d35AA1918",
      "lng": 106.635528
    },
    {
      "id": 1,
      "lat": 27.080285,
      "vehicle_card": "\u8d35AA4507",
      "lng": 106.886876
    },
    {
      "id": 1,
      "lat": 26.676981,
      "vehicle_card": "\u8d35A32205",
      "lng": 106.71305
    },
    {
      "id": 1,
      "lat": 27.073968,
      "vehicle_card": "\u8d35A56894",
      "lng": 106.959541
    },
    {
      "id": 1,
      "lat": 26.693339,
      "vehicle_card": "\u8d35AU4187",
      "lng": 106.623137
    },
    {
      "id": 1,
      "lat": 27.0578,
      "vehicle_card": "\u8d35AUA589",
      "lng": 106.989813
    },
    {
      "id": 1,
      "lat": 26.681283,
      "vehicle_card": "\u8d35AU5625",
      "lng": 106.63788
    },
    {
      "id": 1,
      "lat": 26.556655,
      "vehicle_card": "\u8d35AU9816",
      "lng": 106.467991
    },
    {
      "id": 1,
      "lat": 27.053672,
      "vehicle_card": "\u8d35A65529",
      "lng": 106.968528
    },
    {
      "id": 1,
      "lat": 27.066311,
      "vehicle_card": "\u8d35AU7127",
      "lng": 106.962396
    },
    {
      "id": 1,
      "lat": 27.055906,
      "vehicle_card": "\u8d35A48007",
      "lng": 106.764713
    },
    {
      "id": 1,
      "lat": 27.046691,
      "vehicle_card": "\u8d35AU7136",
      "lng": 106.844369
    },
    {
      "id": 1,
      "lat": 26.49671,
      "vehicle_card": "\u8d35AU4812",
      "lng": 106.661123
    },
    {
      "id": 1,
      "lat": 26.598723,
      "vehicle_card": "\u8d35A43929",
      "lng": 106.576596
    },
    {
      "id": 1,
      "lat": 26.844445,
      "vehicle_card": "\u8d35A54572",
      "lng": 106.598538
    },
    {
      "id": 1,
      "lat": 26.597442,
      "vehicle_card": "\u8d35AA2909",
      "lng": 106.57759
    },
    {
      "id": 1,
      "lat": 26.562189,
      "vehicle_card": "\u8d35A57155",
      "lng": 106.701591
    },
    {
      "id": 1,
      "lat": 26.634126,
      "vehicle_card": "\u8d35A54868",
      "lng": 106.749155
    },
    {
      "id": 1,
      "lat": 26.597795,
      "vehicle_card": "\u8d35A88808",
      "lng": 106.576896
    },
    {
      "id": 1,
      "lat": 26.607823,
      "vehicle_card": "\u8d35A74321",
      "lng": 106.575815
    },
    {
      "id": 1,
      "lat": 26.598251,
      "vehicle_card": "\u8d35A45963",
      "lng": 106.577041
    },
    {
      "id": 1,
      "lat": 26.524753,
      "vehicle_card": "\u8d35A23868",
      "lng": 106.771621
    },
    {
      "id": 1,
      "lat": 26.52534,
      "vehicle_card": "\u8d35A57855",
      "lng": 106.772358
    },
    {
      "id": 1,
      "lat": 26.635597,
      "vehicle_card": "\u8d35A77065",
      "lng": 106.767764
    },
    {
      "id": 1,
      "lat": 26.598898,
      "vehicle_card": "\u8d35A77449",
      "lng": 106.576283
    },
    {
      "id": 1,
      "lat": 27.091354,
      "vehicle_card": "\u8d35A72853",
      "lng": 106.733413
    },
    {
      "id": 1,
      "lat": 26.677289,
      "vehicle_card": "\u8d35A83051",
      "lng": 106.771076
    },
    {
      "id": 1,
      "lat": 26.713741,
      "vehicle_card": "\u8d35A51829",
      "lng": 106.68439
    },
    {
      "id": 1,
      "lat": 27.053091,
      "vehicle_card": "\u8d35AU9879",
      "lng": 106.967531
    },
    {
      "id": 1,
      "lat": 26.598026,
      "vehicle_card": "\u8d35A43812",
      "lng": 106.576026
    },
    {
      "id": 1,
      "lat": 26.598518,
      "vehicle_card": "\u8d35A52167",
      "lng": 106.575607
    },
    {
      "id": 1,
      "lat": 26.6846,
      "vehicle_card": "\u8d35A01668",
      "lng": 106.630126
    },
    {
      "id": 1,
      "lat": 27.066957,
      "vehicle_card": "\u8d35AUB179",
      "lng": 106.963673
    },
    {
      "id": 1,
      "lat": 26.632977,
      "vehicle_card": "\u8d35AU5363",
      "lng": 106.763799
    },
    {
      "id": 1,
      "lat": 26.475975,
      "vehicle_card": "\u8d35AU3248",
      "lng": 106.658966
    },
    {
      "id": 1,
      "lat": 26.600865,
      "vehicle_card": "\u8d35A78198",
      "lng": 106.581416
    },
    {
      "id": 1,
      "lat": 26.586706,
      "vehicle_card": "\u8d35AT5122",
      "lng": 106.695465
    },
    {
      "id": 1,
      "lat": 27.063145,
      "vehicle_card": "\u8d35AUA932",
      "lng": 106.958352
    },
    {
      "id": 1,
      "lat": 27.066654,
      "vehicle_card": "\u8d35AA8552",
      "lng": 106.668899
    },
    {
      "id": 1,
      "lat": 26.596788,
      "vehicle_card": "\u8d35A37586",
      "lng": 106.576968
    },
    {
      "id": 1,
      "lat": 26.636969,
      "vehicle_card": "\u8d35A83187",
      "lng": 106.768502
    },
    {
      "id": 1,
      "lat": 26.59938,
      "vehicle_card": "\u8d35A01136",
      "lng": 106.575622
    },
    {
      "id": 1,
      "lat": 26.596326,
      "vehicle_card": "\u8d35AA9785",
      "lng": 106.577636
    },
    {
      "id": 1,
      "lat": 26.619791,
      "vehicle_card": "\u8d35AT2106",
      "lng": 106.633338
    },
    {
      "id": 1,
      "lat": 26.599165,
      "vehicle_card": "\u8d35AU4840",
      "lng": 106.578121
    },
    {
      "id": 1,
      "lat": 26.593875,
      "vehicle_card": "\u8d35A72285",
      "lng": 106.672923
    },
    {
      "id": 1,
      "lat": 26.547767,
      "vehicle_card": "\u8d35A64915",
      "lng": 106.456205
    },
    {
      "id": 1,
      "lat": 26.584212,
      "vehicle_card": "\u8d35A41061",
      "lng": 106.665559
    },
    {
      "id": 1,
      "lat": 26.583539,
      "vehicle_card": "\u8d35A38771",
      "lng": 106.675105
    },
    {
      "id": 1,
      "lat": 26.935795,
      "vehicle_card": "\u8d35A87325",
      "lng": 106.69599
    },
    {
      "id": 1,
      "lat": 26.989633,
      "vehicle_card": "\u8d35A65916",
      "lng": 106.941735
    },
    {
      "id": 1,
      "lat": 26.570508,
      "vehicle_card": "\u8d35A78202",
      "lng": 106.652175
    },
    {
      "id": 1,
      "lat": 26.59849,
      "vehicle_card": "\u8d35A01111",
      "lng": 106.576485
    },
    {
      "id": 1,
      "lat": 27.097501,
      "vehicle_card": "\u8d35AUA354",
      "lng": 106.736493
    },
    {
      "id": 1,
      "lat": 26.589598,
      "vehicle_card": "\u8d35AT5262",
      "lng": 106.698863
    },
    {
      "id": 1,
      "lat": 26.582778,
      "vehicle_card": "\u8d35A46020",
      "lng": 106.537879
    },
    {
      "id": 1,
      "lat": 26.670631,
      "vehicle_card": "\u8d35AU5366",
      "lng": 106.70871
    },
    {
      "id": 1,
      "lat": 26.484408,
      "vehicle_card": "\u8d35A71902",
      "lng": 106.668778
    },
    {
      "id": 1,
      "lat": 26.599411,
      "vehicle_card": "\u8d35A83266",
      "lng": 106.575386
    },
    {
      "id": 1,
      "lat": 27.09943,
      "vehicle_card": "\u8d35A82788",
      "lng": 106.730971
    },
    {
      "id": 1,
      "lat": 26.613095,
      "vehicle_card": "\u8d35A48534",
      "lng": 106.724365
    },
    {
      "id": 1,
      "lat": 26.573681,
      "vehicle_card": "\u8d35A58416",
      "lng": 106.46524
    },
    {
      "id": 1,
      "lat": 26.868523,
      "vehicle_card": "\u8d35A47004",
      "lng": 106.708468
    },
    {
      "id": 1,
      "lat": 26.579313,
      "vehicle_card": "\u8d35AU4929",
      "lng": 106.659485
    },
    {
      "id": 1,
      "lat": 26.598793,
      "vehicle_card": "\u8d35A72727",
      "lng": 106.576522
    },
    {
      "id": 1,
      "lat": 26.598577,
      "vehicle_card": "\u8d35A40036",
      "lng": 106.576263
    },
    {
      "id": 1,
      "lat": 26.597517,
      "vehicle_card": "\u8d35A48330",
      "lng": 106.576622
    },
    {
      "id": 1,
      "lat": 27.072373,
      "vehicle_card": "\u8d35A72841",
      "lng": 106.602848
    },
    {
      "id": 1,
      "lat": 26.586614,
      "vehicle_card": "\u8d35AT5256",
      "lng": 106.694931
    },
    {
      "id": 1,
      "lat": 26.850812,
      "vehicle_card": "\u8d35AU4406",
      "lng": 106.715484
    },
    {
      "id": 1,
      "lat": 27.079507,
      "vehicle_card": "\u8d35A77261",
      "lng": 106.743797
    },
    {
      "id": 1,
      "lat": 27.065374,
      "vehicle_card": "\u8d35AB0700",
      "lng": 106.965438
    },
    {
      "id": 1,
      "lat": 27.052355,
      "vehicle_card": "\u8d35AU9908",
      "lng": 106.968007
    },
    {
      "id": 1,
      "lat": 26.547065,
      "vehicle_card": "\u8d35AU5339",
      "lng": 106.794748
    },
    {
      "id": 1,
      "lat": 27.078945,
      "vehicle_card": "\u8d35A77575",
      "lng": 106.743293
    },
    {
      "id": 1,
      "lat": 26.878467,
      "vehicle_card": "\u8d35AA2949",
      "lng": 107.105514
    },
    {
      "id": 1,
      "lat": 26.483648,
      "vehicle_card": "\u8d35AA0860",
      "lng": 106.737024
    },
    {
      "id": 1,
      "lat": 27.119075,
      "vehicle_card": "\u8d35A43764",
      "lng": 107.112545
    },
    {
      "id": 1,
      "lat": 26.617437,
      "vehicle_card": "\u8d35AU3899",
      "lng": 106.617933
    },
    {
      "id": 1,
      "lat": 26.598523,
      "vehicle_card": "\u8d35A29298",
      "lng": 106.576603
    },
    {
      "id": 1,
      "lat": 27.067967,
      "vehicle_card": "\u8d35AUB948",
      "lng": 106.9673
    },
    {
      "id": 1,
      "lat": 26.575151,
      "vehicle_card": "\u8d35AU5330",
      "lng": 106.725591
    },
    {
      "id": 1,
      "lat": 27.048568,
      "vehicle_card": "\u8d35A88606",
      "lng": 106.737701
    },
    {
      "id": 1,
      "lat": 27.088405,
      "vehicle_card": "\u8d35A87278",
      "lng": 106.740737
    },
    {
      "id": 1,
      "lat": 26.624806,
      "vehicle_card": "\u8d35AU5312",
      "lng": 106.740398
    },
    {
      "id": 1,
      "lat": 26.410488,
      "vehicle_card": "\u8d35AA0753",
      "lng": 106.592385
    },
    {
      "id": 1,
      "lat": 27.061408,
      "vehicle_card": "\u8d35AUA042",
      "lng": 106.966203
    },
    {
      "id": 1,
      "lat": 26.639208,
      "vehicle_card": "\u8d35AU3647",
      "lng": 106.780867
    },
    {
      "id": 1,
      "lat": 27.053513,
      "vehicle_card": "\u8d35AU9922",
      "lng": 106.977651
    },
    {
      "id": 1,
      "lat": 27.055236,
      "vehicle_card": "\u8d35A22180",
      "lng": 106.979066
    },
    {
      "id": 1,
      "lat": 26.597116,
      "vehicle_card": "\u8d35A01066",
      "lng": 106.576339
    },
    {
      "id": 1,
      "lat": 27.111238,
      "vehicle_card": "\u8d35A55347",
      "lng": 106.92106
    },
    {
      "id": 1,
      "lat": 27.047933,
      "vehicle_card": "\u8d35AUB918",
      "lng": 106.974469
    },
    {
      "id": 1,
      "lat": 27.057228,
      "vehicle_card": "\u8d35AUB698",
      "lng": 106.956228
    },
    {
      "id": 1,
      "lat": 26.641776,
      "vehicle_card": "\u8d35A77068",
      "lng": 106.772914
    },
    {
      "id": 1,
      "lat": 26.599471,
      "vehicle_card": "\u8d35A40009",
      "lng": 106.577238
    },
    {
      "id": 1,
      "lat": 26.835805,
      "vehicle_card": "\u8d35A72218",
      "lng": 106.887271
    },
    {
      "id": 1,
      "lat": 26.681594,
      "vehicle_card": "\u8d35AU3773",
      "lng": 106.621476
    },
    {
      "id": 1,
      "lat": 26.655623,
      "vehicle_card": "\u8d35AU4933",
      "lng": 106.619929
    },
    {
      "id": 1,
      "lat": 27.065704,
      "vehicle_card": "\u8d35AB0669",
      "lng": 106.964576
    },
    {
      "id": 1,
      "lat": 26.637161,
      "vehicle_card": "\u8d35A52321",
      "lng": 106.768971
    },
    {
      "id": 1,
      "lat": 26.81922,
      "vehicle_card": "\u8d35AT1146",
      "lng": 106.87638
    },
    {
      "id": 1,
      "lat": 27.113044,
      "vehicle_card": "\u8d35A83021",
      "lng": 106.909759
    },
    {
      "id": 1,
      "lat": 26.626717,
      "vehicle_card": "\u8d35AU5359",
      "lng": 106.746587
    },
    {
      "id": 1,
      "lat": 26.686205,
      "vehicle_card": "\u8d35AU5645",
      "lng": 106.633445
    },
    {
      "id": 1,
      "lat": 27.05762,
      "vehicle_card": "\u8d35AU9827",
      "lng": 106.95975
    },
    {
      "id": 1,
      "lat": 26.851222,
      "vehicle_card": "\u8d35AA9987",
      "lng": 106.592124
    },
    {
      "id": 1,
      "lat": 27.067434,
      "vehicle_card": "\u8d35A82887",
      "lng": 106.967407
    },
    {
      "id": 1,
      "lat": 26.59008,
      "vehicle_card": "\u8d35A78210",
      "lng": 106.700385
    },
    {
      "id": 1,
      "lat": 26.523845,
      "vehicle_card": "\u8d35A77056",
      "lng": 106.771789
    },
    {
      "id": 1,
      "lat": 27.064318,
      "vehicle_card": "\u8d35A47312",
      "lng": 106.943781
    },
    {
      "id": 1,
      "lat": 26.590614,
      "vehicle_card": "\u8d35A53817",
      "lng": 106.795983
    },
    {
      "id": 1,
      "lat": 26.856473,
      "vehicle_card": "\u8d35A67992",
      "lng": 106.686058
    },
    {
      "id": 1,
      "lat": 26.936115,
      "vehicle_card": "\u8d35A65009",
      "lng": 106.923362
    },
    {
      "id": 1,
      "lat": 27.078832,
      "vehicle_card": "\u8d35A77246",
      "lng": 106.743446
    },
    {
      "id": 1,
      "lat": 26.598802,
      "vehicle_card": "\u8d35A22679",
      "lng": 106.575836
    },
    {
      "id": 1,
      "lat": 26.598894,
      "vehicle_card": "\u8d35A32215",
      "lng": 106.577095
    },
    {
      "id": 1,
      "lat": 27.099632,
      "vehicle_card": "\u8d35AA2899",
      "lng": 106.731552
    },
    {
      "id": 1,
      "lat": 27.079074,
      "vehicle_card": "\u8d35A77557",
      "lng": 106.743255
    },
    {
      "id": 1,
      "lat": 26.586631,
      "vehicle_card": "\u8d35AT5386",
      "lng": 106.695503
    },
    {
      "id": 1,
      "lat": 26.536201,
      "vehicle_card": "\u8d35AT0365",
      "lng": 106.78809
    },
    {
      "id": 1,
      "lat": 26.482256,
      "vehicle_card": "\u8d35A61964",
      "lng": 106.735568
    },
    {
      "id": 1,
      "lat": 26.586202,
      "vehicle_card": "\u8d35A77635",
      "lng": 106.695678
    },
    {
      "id": 1,
      "lat": 26.597402,
      "vehicle_card": "\u8d35A01091",
      "lng": 106.576225
    },
    {
      "id": 1,
      "lat": 27.079261,
      "vehicle_card": "\u8d35A77651",
      "lng": 106.74353
    },
    {
      "id": 1,
      "lat": 26.632036,
      "vehicle_card": "\u8d35A707L7",
      "lng": 106.756189
    },
    {
      "id": 1,
      "lat": 26.635015,
      "vehicle_card": "\u8d35AA2875",
      "lng": 106.581016
    },
    {
      "id": 1,
      "lat": 27.066263,
      "vehicle_card": "\u8d35AUA752",
      "lng": 106.959588
    },
    {
      "id": 1,
      "lat": 26.812918,
      "vehicle_card": "\u8d35A77576",
      "lng": 107.043016
    },
    {
      "id": 1,
      "lat": 26.607326,
      "vehicle_card": "\u8d35AU9860",
      "lng": 106.721249
    },
    {
      "id": 1,
      "lat": 26.349026,
      "vehicle_card": "\u8d35A43324",
      "lng": 106.673138
    },
    {
      "id": 1,
      "lat": 26.868906,
      "vehicle_card": "\u8d35A52334",
      "lng": 106.709365
    },
    {
      "id": 1,
      "lat": 27.078748,
      "vehicle_card": "\u8d35A83391",
      "lng": 106.743606
    },
    {
      "id": 1,
      "lat": 26.444083,
      "vehicle_card": "\u8d35A37793",
      "lng": 106.673201
    },
    {
      "id": 1,
      "lat": 26.596433,
      "vehicle_card": "\u8d35A65354",
      "lng": 106.577428
    },
    {
      "id": 1,
      "lat": 26.606845,
      "vehicle_card": "\u8d35AA1865",
      "lng": 106.72047
    },
    {
      "id": 1,
      "lat": 26.627095,
      "vehicle_card": "\u8d35AU5662",
      "lng": 106.747385
    },
    {
      "id": 1,
      "lat": 26.692043,
      "vehicle_card": "\u8d35AU5626",
      "lng": 106.645956
    },
    {
      "id": 1,
      "lat": 26.53077,
      "vehicle_card": "\u8d35AU4884",
      "lng": 106.693553
    },
    {
      "id": 1,
      "lat": 26.558096,
      "vehicle_card": "\u8d35A33033",
      "lng": 106.472341
    },
    {
      "id": 1,
      "lat": 27.108343,
      "vehicle_card": "\u8d35AUA676",
      "lng": 106.729168
    },
    {
      "id": 1,
      "lat": 27.097326,
      "vehicle_card": "\u8d35AUA668",
      "lng": 106.735946
    },
    {
      "id": 1,
      "lat": 26.586455,
      "vehicle_card": "\u8d35AT5287",
      "lng": 106.695686
    },
    {
      "id": 1,
      "lat": 26.552339,
      "vehicle_card": "\u8d35AGH021",
      "lng": 106.6571
    },
    {
      "id": 1,
      "lat": 26.598886,
      "vehicle_card": "\u8d35AA4578",
      "lng": 106.577486
    },
    {
      "id": 1,
      "lat": 27.059965,
      "vehicle_card": "\u8d35AUA511",
      "lng": 106.747778
    },
    {
      "id": 1,
      "lat": 26.501403,
      "vehicle_card": "\u8d35A38426",
      "lng": 106.662515
    },
    {
      "id": 1,
      "lat": 27.09685,
      "vehicle_card": "\u8d35AUA508",
      "lng": 106.726313
    },
    {
      "id": 1,
      "lat": 27.079913,
      "vehicle_card": "\u8d35AUA663",
      "lng": 106.741943
    },
    {
      "id": 1,
      "lat": 27.101541,
      "vehicle_card": "\u8d35AUA672",
      "lng": 106.730476
    },
    {
      "id": 1,
      "lat": 27.096611,
      "vehicle_card": "\u8d35AUA669",
      "lng": 106.73383
    },
    {
      "id": 1,
      "lat": 27.086191,
      "vehicle_card": "\u8d35AUA471",
      "lng": 106.738555
    },
    {
      "id": 1,
      "lat": 27.096786,
      "vehicle_card": "\u8d35AUA563",
      "lng": 106.726223
    },
    {
      "id": 1,
      "lat": 26.586643,
      "vehicle_card": "\u8d35AT5177",
      "lng": 106.695304
    },
    {
      "id": 1,
      "lat": 26.862565,
      "vehicle_card": "\u8d35A49579",
      "lng": 106.706458
    },
    {
      "id": 1,
      "lat": 26.557685,
      "vehicle_card": "\u8d35AT5278",
      "lng": 106.471756
    },
    {
      "id": 1,
      "lat": 26.545424,
      "vehicle_card": "\u8d35AT0069",
      "lng": 106.679768
    },
    {
      "id": 1,
      "lat": 27.060886,
      "vehicle_card": "\u8d35AU9346",
      "lng": 106.960425
    },
    {
      "id": 1,
      "lat": 26.557686,
      "vehicle_card": "\u8d35AT5282",
      "lng": 106.471575
    },
    {
      "id": 1,
      "lat": 27.064605,
      "vehicle_card": "\u8d35A54842",
      "lng": 106.964411
    },
    {
      "id": 1,
      "lat": 26.619261,
      "vehicle_card": "\u8d35AFF079",
      "lng": 106.653341
    },
    {
      "id": 1,
      "lat": 26.537355,
      "vehicle_card": "\u8d35A35996",
      "lng": 106.666045
    },
    {
      "id": 1,
      "lat": 26.53091,
      "vehicle_card": "\u8d35A46780",
      "lng": 106.757526
    },
    {
      "id": 1,
      "lat": 26.597903,
      "vehicle_card": "\u8d35A77289",
      "lng": 106.576601
    },
    {
      "id": 1,
      "lat": 26.599023,
      "vehicle_card": "\u8d35A49698",
      "lng": 106.577796
    },
    {
      "id": 1,
      "lat": 26.599538,
      "vehicle_card": "\u8d35AU5568",
      "lng": 106.57737
    },
    {
      "id": 1,
      "lat": 26.524525,
      "vehicle_card": "\u8d35A29843",
      "lng": 106.77286
    },
    {
      "id": 1,
      "lat": 27.010126,
      "vehicle_card": "\u8d35AA3976",
      "lng": 107.08955
    },
    {
      "id": 1,
      "lat": 27.078631,
      "vehicle_card": "\u8d35A77588",
      "lng": 106.74364
    },
    {
      "id": 1,
      "lat": 26.597011,
      "vehicle_card": "\u8d35A77266",
      "lng": 106.576113
    },
    {
      "id": 1,
      "lat": 26.466898,
      "vehicle_card": "\u8d35A61263",
      "lng": 106.684631
    },
    {
      "id": 1,
      "lat": 26.775475,
      "vehicle_card": "\u8d35A82717",
      "lng": 106.746575
    },
    {
      "id": 1,
      "lat": 26.598886,
      "vehicle_card": "\u8d35A12666",
      "lng": 106.57697
    },
    {
      "id": 1,
      "lat": 26.864408,
      "vehicle_card": "\u8d35AA4536",
      "lng": 107.02801
    },
    {
      "id": 1,
      "lat": 26.616868,
      "vehicle_card": "\u8d35AU4811",
      "lng": 106.583976
    },
    {
      "id": 1,
      "lat": 26.603605,
      "vehicle_card": "\u8d35AA2787",
      "lng": 106.764261
    },
    {
      "id": 1,
      "lat": 26.703131,
      "vehicle_card": "\u8d35A78399",
      "lng": 106.688106
    },
    {
      "id": 1,
      "lat": 27.055581,
      "vehicle_card": "\u8d35A87323",
      "lng": 106.746606
    },
    {
      "id": 1,
      "lat": 26.597388,
      "vehicle_card": "\u8d35A01166",
      "lng": 106.57628
    },
    {
      "id": 1,
      "lat": 26.738615,
      "vehicle_card": "\u8d35A83052",
      "lng": 106.358355
    },
    {
      "id": 1,
      "lat": 26.6617,
      "vehicle_card": "\u8d35A32279",
      "lng": 106.704855
    },
    {
      "id": 1,
      "lat": 27.058396,
      "vehicle_card": "\u8d35AU9106",
      "lng": 106.964955
    },
    {
      "id": 1,
      "lat": 27.095471,
      "vehicle_card": "\u8d35AUA677",
      "lng": 106.732246
    },
    {
      "id": 1,
      "lat": 27.119255,
      "vehicle_card": "\u8d35A87364",
      "lng": 106.676
    },
    {
      "id": 1,
      "lat": 27.122503,
      "vehicle_card": "\u8d35A72842",
      "lng": 106.653853
    },
    {
      "id": 1,
      "lat": 26.597413,
      "vehicle_card": "\u8d35A86366",
      "lng": 106.576885
    },
    {
      "id": 1,
      "lat": 27.097306,
      "vehicle_card": "\u8d35AA1655",
      "lng": 106.71181
    },
    {
      "id": 1,
      "lat": 26.597463,
      "vehicle_card": "\u8d35A46965",
      "lng": 106.577209
    },
    {
      "id": 1,
      "lat": 27.0792,
      "vehicle_card": "\u8d35A77252",
      "lng": 106.743541
    },
    {
      "id": 1,
      "lat": 26.561993,
      "vehicle_card": "\u8d35A49165",
      "lng": 106.701506
    },
    {
      "id": 1,
      "lat": 26.95264,
      "vehicle_card": "\u8d35ALL407",
      "lng": 106.687778
    },
    {
      "id": 1,
      "lat": 26.610187,
      "vehicle_card": "\u8d35AT1211",
      "lng": 106.720333
    },
    {
      "id": 1,
      "lat": 26.846771,
      "vehicle_card": "\u8d35A49743",
      "lng": 106.598875
    },
    {
      "id": 1,
      "lat": 26.530707,
      "vehicle_card": "\u8d35AT1607",
      "lng": 106.784535
    },
    {
      "id": 1,
      "lat": 26.586143,
      "vehicle_card": "\u8d35AT0391",
      "lng": 106.707388
    },
    {
      "id": 1,
      "lat": 27.003953,
      "vehicle_card": "\u8d35AU9358",
      "lng": 106.93859
    },
    {
      "id": 1,
      "lat": 26.64704,
      "vehicle_card": "\u8d35AU9868",
      "lng": 106.757346
    },
    {
      "id": 1,
      "lat": 26.617318,
      "vehicle_card": "\u8d35AU4839",
      "lng": 106.609211
    },
    {
      "id": 1,
      "lat": 26.601463,
      "vehicle_card": "\u8d35AU9362",
      "lng": 106.714801
    },
    {
      "id": 1,
      "lat": 27.134638,
      "vehicle_card": "\u8d35AA9639",
      "lng": 106.718195
    },
    {
      "id": 1,
      "lat": 26.440055,
      "vehicle_card": "\u8d35AU6696",
      "lng": 106.67401
    },
    {
      "id": 1,
      "lat": 26.524164,
      "vehicle_card": "\u8d35A48870",
      "lng": 106.771995
    },
    {
      "id": 1,
      "lat": 26.607506,
      "vehicle_card": "\u8d35A77633",
      "lng": 106.358056
    },
    {
      "id": 1,
      "lat": 26.775475,
      "vehicle_card": "\u8d35A501B7",
      "lng": 106.746833
    },
    {
      "id": 1,
      "lat": 27.079547,
      "vehicle_card": "\u8d35A82779",
      "lng": 106.743881
    },
    {
      "id": 1,
      "lat": 27.114856,
      "vehicle_card": "\u8d35A83269",
      "lng": 106.843376
    },
    {
      "id": 1,
      "lat": 26.598376,
      "vehicle_card": "\u8d35A77403",
      "lng": 106.575773
    },
    {
      "id": 1,
      "lat": 26.981428,
      "vehicle_card": "\u8d35A87244",
      "lng": 106.682528
    },
    {
      "id": 1,
      "lat": 26.989323,
      "vehicle_card": "\u8d35AA9585",
      "lng": 106.784521
    },
    {
      "id": 1,
      "lat": 27.065066,
      "vehicle_card": "\u8d35AU9248",
      "lng": 106.94599
    },
    {
      "id": 1,
      "lat": 26.613445,
      "vehicle_card": "\u8d35A77238",
      "lng": 106.582563
    },
    {
      "id": 1,
      "lat": 27.064423,
      "vehicle_card": "\u8d35AU8792",
      "lng": 106.963155
    },
    {
      "id": 1,
      "lat": 27.0663,
      "vehicle_card": "\u8d35AU9880",
      "lng": 106.962411
    },
    {
      "id": 1,
      "lat": 27.053421,
      "vehicle_card": "\u8d35AU9351",
      "lng": 106.979455
    },
    {
      "id": 1,
      "lat": 27.079148,
      "vehicle_card": "\u8d35AU9885",
      "lng": 106.959721
    },
    {
      "id": 1,
      "lat": 26.59794,
      "vehicle_card": "\u8d35A89771",
      "lng": 106.576828
    },
    {
      "id": 1,
      "lat": 26.635783,
      "vehicle_card": "\u8d35A57187",
      "lng": 106.766731
    },
    {
      "id": 1,
      "lat": 26.833961,
      "vehicle_card": "\u8d35AU9348",
      "lng": 106.887613
    },
    {
      "id": 1,
      "lat": 26.592818,
      "vehicle_card": "\u8d35AT2127",
      "lng": 106.699735
    },
    {
      "id": 1,
      "lat": 26.458785,
      "vehicle_card": "\u8d35AU6608",
      "lng": 106.586143
    },
    {
      "id": 1,
      "lat": 27.056293,
      "vehicle_card": "\u8d35AU9886",
      "lng": 106.976983
    },
    {
      "id": 1,
      "lat": 27.067163,
      "vehicle_card": "\u8d35AU9311",
      "lng": 106.948493
    },
    {
      "id": 1,
      "lat": 26.597818,
      "vehicle_card": "\u8d35A50683",
      "lng": 106.577278
    },
    {
      "id": 1,
      "lat": 27.062871,
      "vehicle_card": "\u8d35AU9105",
      "lng": 106.965998
    },
    {
      "id": 1,
      "lat": 26.601298,
      "vehicle_card": "\u8d35AT1802",
      "lng": 106.636566
    },
    {
      "id": 1,
      "lat": 26.528843,
      "vehicle_card": "\u8d35AT1990",
      "lng": 106.697391
    },
    {
      "id": 1,
      "lat": 27.049941,
      "vehicle_card": "\u8d35A83566",
      "lng": 106.574561
    },
    {
      "id": 1,
      "lat": 26.599885,
      "vehicle_card": "\u8d35A57228",
      "lng": 106.575331
    },
    {
      "id": 1,
      "lat": 27.050935,
      "vehicle_card": "\u8d35A89714",
      "lng": 106.985588
    },
    {
      "id": 1,
      "lat": 27.171554,
      "vehicle_card": "\u8d35AA9591",
      "lng": 106.722984
    },
    {
      "id": 1,
      "lat": 26.59972,
      "vehicle_card": "\u8d35A54851",
      "lng": 106.575248
    },
    {
      "id": 1,
      "lat": 26.562273,
      "vehicle_card": "\u8d35A37851",
      "lng": 106.701606
    },
    {
      "id": 1,
      "lat": 27.065925,
      "vehicle_card": "\u8d35AA9631",
      "lng": 106.964806
    },
    {
      "id": 1,
      "lat": 26.880147,
      "vehicle_card": "\u8d35AA3783",
      "lng": 107.105041
    },
    {
      "id": 1,
      "lat": 26.598531,
      "vehicle_card": "\u8d35A63754",
      "lng": 106.576666
    },
    {
      "id": 1,
      "lat": 26.662896,
      "vehicle_card": "\u8d35A89796",
      "lng": 106.704501
    },
    {
      "id": 1,
      "lat": 27.087268,
      "vehicle_card": "\u8d35A52323",
      "lng": 106.705288
    },
    {
      "id": 1,
      "lat": 26.433708,
      "vehicle_card": "\u8d35A57493",
      "lng": 106.67237
    },
    {
      "id": 1,
      "lat": 27.067201,
      "vehicle_card": "\u8d35AU9108",
      "lng": 106.97676
    },
    {
      "id": 1,
      "lat": 26.636543,
      "vehicle_card": "\u8d35A45314",
      "lng": 106.356125
    },
    {
      "id": 1,
      "lat": 26.596808,
      "vehicle_card": "\u8d35A51327",
      "lng": 106.576343
    },
    {
      "id": 1,
      "lat": 27.067737,
      "vehicle_card": "\u8d35AA7029",
      "lng": 106.967399
    },
    {
      "id": 1,
      "lat": 26.814831,
      "vehicle_card": "\u8d35A54867",
      "lng": 106.875668
    },
    {
      "id": 1,
      "lat": 27.017419,
      "vehicle_card": "\u8d35A78267",
      "lng": 107.047927
    },
    {
      "id": 1,
      "lat": 27.078948,
      "vehicle_card": "\u8d35A72863",
      "lng": 106.743247
    },
    {
      "id": 1,
      "lat": 26.525373,
      "vehicle_card": "\u8d35A31557",
      "lng": 106.772842
    },
    {
      "id": 1,
      "lat": 26.5966,
      "vehicle_card": "\u8d35A32246",
      "lng": 106.577055
    },
    {
      "id": 1,
      "lat": 26.562935,
      "vehicle_card": "\u8d35A72143",
      "lng": 106.683446
    },
    {
      "id": 1,
      "lat": 26.586351,
      "vehicle_card": "\u8d35A61586",
      "lng": 106.695373
    },
    {
      "id": 1,
      "lat": 26.97645,
      "vehicle_card": "\u8d35A68638",
      "lng": 106.689186
    },
    {
      "id": 1,
      "lat": 26.59884,
      "vehicle_card": "\u8d35A56974",
      "lng": 106.575833
    },
    {
      "id": 1,
      "lat": 27.06631,
      "vehicle_card": "\u8d35A01567",
      "lng": 106.964083
    },
    {
      "id": 1,
      "lat": 27.07913,
      "vehicle_card": "\u8d35A77248",
      "lng": 106.743555
    },
    {
      "id": 1,
      "lat": 27.099416,
      "vehicle_card": "\u8d35A87490",
      "lng": 106.730853
    },
    {
      "id": 1,
      "lat": 27.08004,
      "vehicle_card": "\u8d35AU9366",
      "lng": 106.90325
    },
    {
      "id": 1,
      "lat": 26.925968,
      "vehicle_card": "\u8d35A77445",
      "lng": 107.013095
    },
    {
      "id": 1,
      "lat": 26.59782,
      "vehicle_card": "\u8d35AA2656",
      "lng": 106.576233
    },
    {
      "id": 1,
      "lat": 26.571621,
      "vehicle_card": "\u8d35AU4915",
      "lng": 106.653675
    },
    {
      "id": 1,
      "lat": 26.598934,
      "vehicle_card": "\u8d35A83168",
      "lng": 106.575866
    },
    {
      "id": 1,
      "lat": 27.068458,
      "vehicle_card": "\u8d35A70757",
      "lng": 107.057516
    },
    {
      "id": 1,
      "lat": 27.065734,
      "vehicle_card": "\u8d35A49560",
      "lng": 106.965179
    },
    {
      "id": 1,
      "lat": 27.097929,
      "vehicle_card": "\u8d35A72860",
      "lng": 106.715202
    },
    {
      "id": 1,
      "lat": 26.525457,
      "vehicle_card": "\u8d35A36071",
      "lng": 106.77285
    },
    {
      "id": 1,
      "lat": 26.923231,
      "vehicle_card": "\u8d35A63985",
      "lng": 106.964386
    },
    {
      "id": 1,
      "lat": 26.596408,
      "vehicle_card": "\u8d35A30066",
      "lng": 106.577393
    },
    {
      "id": 1,
      "lat": 27.037213,
      "vehicle_card": "\u8d35A56663",
      "lng": 106.939748
    },
    {
      "id": 1,
      "lat": 26.552328,
      "vehicle_card": "\u8d35AU4920",
      "lng": 106.68484
    },
    {
      "id": 1,
      "lat": 26.622036,
      "vehicle_card": "\u8d35AU3849",
      "lng": 106.734833
    },
    {
      "id": 1,
      "lat": 26.5506,
      "vehicle_card": "\u8d35AA3232",
      "lng": 106.795813
    },
    {
      "id": 1,
      "lat": 26.598903,
      "vehicle_card": "\u8d35A54814",
      "lng": 106.575931
    },
    {
      "id": 1,
      "lat": 26.593688,
      "vehicle_card": "\u8d35A87076",
      "lng": 106.394061
    },
    {
      "id": 1,
      "lat": 26.566783,
      "vehicle_card": "\u8d35AU6036",
      "lng": 106.68303
    },
    {
      "id": 1,
      "lat": 26.597341,
      "vehicle_card": "\u8d35A42615",
      "lng": 106.576523
    },
    {
      "id": 1,
      "lat": 27.068067,
      "vehicle_card": "\u8d35A55321",
      "lng": 106.967643
    },
    {
      "id": 1,
      "lat": 26.681991,
      "vehicle_card": "\u8d35AU5619",
      "lng": 106.631588
    },
    {
      "id": 1,
      "lat": 26.483805,
      "vehicle_card": "\u8d35A69743",
      "lng": 106.736261
    },
    {
      "id": 1,
      "lat": 27.136421,
      "vehicle_card": "\u8d35AA1921",
      "lng": 106.717651
    },
    {
      "id": 1,
      "lat": 27.0677,
      "vehicle_card": "\u8d35A65810",
      "lng": 106.936066
    },
    {
      "id": 1,
      "lat": 26.595496,
      "vehicle_card": "\u8d35AA3175",
      "lng": 106.70092
    },
    {
      "id": 1,
      "lat": 27.114935,
      "vehicle_card": "\u8d35A88559",
      "lng": 106.842958
    },
    {
      "id": 1,
      "lat": 27.081146,
      "vehicle_card": "\u8d35AUA678",
      "lng": 106.741235
    },
    {
      "id": 1,
      "lat": 26.894211,
      "vehicle_card": "\u8d35A77263",
      "lng": 106.696828
    },
    {
      "id": 1,
      "lat": 26.599459,
      "vehicle_card": "\u8d35AU3885",
      "lng": 106.578052
    },
    {
      "id": 1,
      "lat": 26.621408,
      "vehicle_card": "\u8d35AT7002",
      "lng": 106.694815
    },
    {
      "id": 1,
      "lat": 27.066827,
      "vehicle_card": "\u8d35A81919",
      "lng": 106.963523
    },
    {
      "id": 1,
      "lat": 26.575889,
      "vehicle_card": "\u8d35A43735",
      "lng": 106.494328
    },
    {
      "id": 1,
      "lat": 26.632118,
      "vehicle_card": "\u8d35AU3987",
      "lng": 106.758431
    },
    {
      "id": 1,
      "lat": 27.056165,
      "vehicle_card": "\u8d35AU9928",
      "lng": 106.972786
    },
    {
      "id": 1,
      "lat": 26.934755,
      "vehicle_card": "\u8d35A45302",
      "lng": 106.700263
    },
    {
      "id": 1,
      "lat": 26.638803,
      "vehicle_card": "\u8d35A57463",
      "lng": 106.642451
    },
    {
      "id": 1,
      "lat": 26.682136,
      "vehicle_card": "\u8d35A58364",
      "lng": 106.471854
    },
    {
      "id": 1,
      "lat": 27.055149,
      "vehicle_card": "\u8d35A47458",
      "lng": 106.851317
    },
    {
      "id": 1,
      "lat": 26.850976,
      "vehicle_card": "\u8d35AU5868",
      "lng": 106.715461
    },
    {
      "id": 1,
      "lat": 26.651836,
      "vehicle_card": "\u8d35AU5799",
      "lng": 106.768617
    },
    {
      "id": 1,
      "lat": 26.557686,
      "vehicle_card": "\u8d35AU9819",
      "lng": 106.461103
    },
    {
      "id": 1,
      "lat": 26.534596,
      "vehicle_card": "\u8d35AT5078",
      "lng": 106.445827
    },
    {
      "id": 1,
      "lat": 26.475037,
      "vehicle_card": "\u8d35A50428",
      "lng": 106.740901
    },
    {
      "id": 1,
      "lat": 26.667878,
      "vehicle_card": "\u8d35AU5646",
      "lng": 106.65568
    },
    {
      "id": 1,
      "lat": 27.059227,
      "vehicle_card": "\u8d35AU9926",
      "lng": 106.969743
    },
    {
      "id": 1,
      "lat": 27.140239,
      "vehicle_card": "\u8d35A55589",
      "lng": 106.678672
    },
    {
      "id": 1,
      "lat": 26.541524,
      "vehicle_card": "\u8d35AA8582",
      "lng": 106.478957
    },
    {
      "id": 1,
      "lat": 26.60665,
      "vehicle_card": "\u8d35AW6465",
      "lng": 106.650616
    },
    {
      "id": 1,
      "lat": 27.063405,
      "vehicle_card": "\u8d35AU9890",
      "lng": 106.965626
    },
    {
      "id": 1,
      "lat": 26.562641,
      "vehicle_card": "\u8d35AU5387",
      "lng": 106.734673
    },
    {
      "id": 1,
      "lat": 26.599433,
      "vehicle_card": "\u8d35A77639",
      "lng": 106.576972
    },
    {
      "id": 1,
      "lat": 26.55039,
      "vehicle_card": "\u8d35AT2030",
      "lng": 106.796051
    },
    {
      "id": 1,
      "lat": 27.066043,
      "vehicle_card": "\u8d35A47479",
      "lng": 106.948535
    },
    {
      "id": 1,
      "lat": 26.599116,
      "vehicle_card": "\u8d35A57458",
      "lng": 106.576634
    },
    {
      "id": 1,
      "lat": 27.043843,
      "vehicle_card": "\u8d35AUA735",
      "lng": 106.986995
    },
    {
      "id": 1,
      "lat": 26.573432,
      "vehicle_card": "\u8d35ARP433",
      "lng": 106.608291
    },
    {
      "id": 1,
      "lat": 26.608013,
      "vehicle_card": "\u8d35AU3916",
      "lng": 106.721818
    },
    {
      "id": 1,
      "lat": 27.092257,
      "vehicle_card": "\u8d35AA2697",
      "lng": 106.741779
    },
    {
      "id": 1,
      "lat": 26.541017,
      "vehicle_card": "\u8d35AA8531",
      "lng": 106.478484
    },
    {
      "id": 1,
      "lat": 27.058956,
      "vehicle_card": "\u8d35AUB478",
      "lng": 106.970321
    },
    {
      "id": 1,
      "lat": 26.919653,
      "vehicle_card": "\u8d35A57693",
      "lng": 106.896531
    },
    {
      "id": 1,
      "lat": 27.050158,
      "vehicle_card": "\u8d35A47478",
      "lng": 106.849494
    },
    {
      "id": 1,
      "lat": 26.583229,
      "vehicle_card": "\u8d35AU5383",
      "lng": 106.701723
    },
    {
      "id": 1,
      "lat": 27.059452,
      "vehicle_card": "\u8d35AU9882",
      "lng": 106.969495
    },
    {
      "id": 1,
      "lat": 27.065241,
      "vehicle_card": "\u8d35AUA041",
      "lng": 106.959418
    },
    {
      "id": 1,
      "lat": 26.506304,
      "vehicle_card": "\u8d35AU8165",
      "lng": 106.703685
    },
    {
      "id": 1,
      "lat": 27.169443,
      "vehicle_card": "\u8d35A38713",
      "lng": 106.999205
    },
    {
      "id": 1,
      "lat": 26.621758,
      "vehicle_card": "\u8d35AU5362",
      "lng": 106.618862
    },
    {
      "id": 1,
      "lat": 26.5878,
      "vehicle_card": "\u8d35A41048",
      "lng": 106.422094
    },
    {
      "id": 1,
      "lat": 26.950276,
      "vehicle_card": "\u8d35A88815",
      "lng": 106.920539
    },
    {
      "id": 1,
      "lat": 26.59943,
      "vehicle_card": "\u8d35A77296",
      "lng": 106.576468
    },
    {
      "id": 1,
      "lat": 27.058735,
      "vehicle_card": "\u8d35A55550",
      "lng": 107.002862
    },
    {
      "id": 1,
      "lat": 26.706903,
      "vehicle_card": "\u8d35A87485",
      "lng": 106.461015
    },
    {
      "id": 1,
      "lat": 26.56718,
      "vehicle_card": "\u8d35A78205",
      "lng": 106.497651
    },
    {
      "id": 1,
      "lat": 26.59863,
      "vehicle_card": "\u8d35AA1857",
      "lng": 106.576911
    },
    {
      "id": 1,
      "lat": 27.046798,
      "vehicle_card": "\u8d35A53023",
      "lng": 106.736965
    },
    {
      "id": 1,
      "lat": 26.686536,
      "vehicle_card": "\u8d35AT0197",
      "lng": 106.65144
    },
    {
      "id": 1,
      "lat": 27.07521,
      "vehicle_card": "\u8d35A65359",
      "lng": 107.03646
    },
    {
      "id": 1,
      "lat": 26.557665,
      "vehicle_card": "\u8d35AT5298",
      "lng": 106.471716
    },
    {
      "id": 1,
      "lat": 26.617333,
      "vehicle_card": "\u8d35A42610",
      "lng": 106.583796
    },
    {
      "id": 1,
      "lat": 27.05373,
      "vehicle_card": "\u8d35A65295",
      "lng": 106.977781
    },
    {
      "id": 1,
      "lat": 27.079538,
      "vehicle_card": "\u8d35A77253",
      "lng": 106.743818
    },
    {
      "id": 1,
      "lat": 26.586589,
      "vehicle_card": "\u8d35AT5198",
      "lng": 106.695556
    },
    {
      "id": 1,
      "lat": 26.627754,
      "vehicle_card": "\u8d35AU5316",
      "lng": 106.748008
    },
    {
      "id": 1,
      "lat": 26.53281,
      "vehicle_card": "\u8d35A77682",
      "lng": 106.728057
    },
    {
      "id": 1,
      "lat": 26.597455,
      "vehicle_card": "\u8d35A01199",
      "lng": 106.576782
    },
    {
      "id": 1,
      "lat": 26.527504,
      "vehicle_card": "\u8d35A58374",
      "lng": 106.706489
    },
    {
      "id": 1,
      "lat": 26.586534,
      "vehicle_card": "\u8d35AT2217",
      "lng": 106.694946
    },
    {
      "id": 1,
      "lat": 27.055353,
      "vehicle_card": "\u8d35A47295",
      "lng": 106.855533
    },
    {
      "id": 1,
      "lat": 26.58249,
      "vehicle_card": "\u8d35AU3910",
      "lng": 106.465731
    },
    {
      "id": 1,
      "lat": 26.562796,
      "vehicle_card": "\u8d35A64910",
      "lng": 106.456718
    },
    {
      "id": 1,
      "lat": 26.523225,
      "vehicle_card": "\u8d35AT0822",
      "lng": 106.771998
    },
    {
      "id": 1,
      "lat": 26.540905,
      "vehicle_card": "\u8d35AA1609",
      "lng": 106.478401
    },
    {
      "id": 1,
      "lat": 26.631973,
      "vehicle_card": "\u8d35AA7799",
      "lng": 106.766521
    },
    {
      "id": 1,
      "lat": 26.552211,
      "vehicle_card": "\u8d35A103L1",
      "lng": 106.657056
    },
    {
      "id": 1,
      "lat": 27.064754,
      "vehicle_card": "\u8d35AUB458",
      "lng": 106.955253
    },
    {
      "id": 1,
      "lat": 27.009615,
      "vehicle_card": "\u8d35AB0658",
      "lng": 106.464168
    },
    {
      "id": 1,
      "lat": 26.555934,
      "vehicle_card": "\u8d35A57622",
      "lng": 106.464419
    },
    {
      "id": 1,
      "lat": 26.483992,
      "vehicle_card": "\u8d35AA3588",
      "lng": 106.737066
    },
    {
      "id": 1,
      "lat": 26.45062,
      "vehicle_card": "\u8d35A32656",
      "lng": 106.739105
    },
    {
      "id": 1,
      "lat": 26.696626,
      "vehicle_card": "\u8d35AU3988",
      "lng": 106.863931
    },
    {
      "id": 1,
      "lat": 26.586158,
      "vehicle_card": "\u8d35AT5180",
      "lng": 106.698356
    },
    {
      "id": 1,
      "lat": 27.099445,
      "vehicle_card": "\u8d35AH603L",
      "lng": 106.836213
    },
    {
      "id": 1,
      "lat": 26.771606,
      "vehicle_card": "\u8d35A57663",
      "lng": 106.556783
    },
    {
      "id": 1,
      "lat": 26.55697,
      "vehicle_card": "\u8d35AU9810",
      "lng": 106.500123
    },
    {
      "id": 1,
      "lat": 26.425875,
      "vehicle_card": "\u8d35A55400",
      "lng": 106.676204
    },
    {
      "id": 1,
      "lat": 27.079025,
      "vehicle_card": "\u8d35A35256",
      "lng": 106.74369
    },
    {
      "id": 1,
      "lat": 26.364164,
      "vehicle_card": "\u8d35A34811",
      "lng": 106.682145
    },
    {
      "id": 1,
      "lat": 26.426705,
      "vehicle_card": "\u8d35A55383",
      "lng": 106.669775
    },
    {
      "id": 1,
      "lat": 26.616765,
      "vehicle_card": "\u8d35AT1350",
      "lng": 106.697816
    },
    {
      "id": 1,
      "lat": 26.507974,
      "vehicle_card": "\u8d35AT1052",
      "lng": 106.672664
    },
    {
      "id": 1,
      "lat": 26.506896,
      "vehicle_card": "\u8d35AT1312",
      "lng": 106.669846
    },
    {
      "id": 1,
      "lat": 26.607327,
      "vehicle_card": "\u8d35AT1102",
      "lng": 106.644752
    },
    {
      "id": 1,
      "lat": 26.608523,
      "vehicle_card": "\u8d35AT1378",
      "lng": 106.722082
    },
    {
      "id": 1,
      "lat": 26.56921,
      "vehicle_card": "\u8d35AT1322",
      "lng": 106.692576
    },
    {
      "id": 1,
      "lat": 26.6597,
      "vehicle_card": "\u8d35A76579",
      "lng": 106.704359
    },
    {
      "id": 1,
      "lat": 26.621161,
      "vehicle_card": "\u8d35AT1339",
      "lng": 106.694182
    },
    {
      "id": 1,
      "lat": 26.687403,
      "vehicle_card": "\u8d35AU5621",
      "lng": 106.653546
    },
    {
      "id": 1,
      "lat": 27.075604,
      "vehicle_card": "\u8d35AUA326",
      "lng": 106.912078
    },
    {
      "id": 1,
      "lat": 26.702366,
      "vehicle_card": "\u8d35AU5627",
      "lng": 106.619088
    },
    {
      "id": 1,
      "lat": 26.691483,
      "vehicle_card": "\u8d35A72797",
      "lng": 106.658943
    },
    {
      "id": 1,
      "lat": 26.576913,
      "vehicle_card": "\u8d35A77384",
      "lng": 106.51782
    },
    {
      "id": 1,
      "lat": 26.604177,
      "vehicle_card": "\u8d35A43337",
      "lng": 106.748246
    },
    {
      "id": 1,
      "lat": 26.706558,
      "vehicle_card": "\u8d35A71364",
      "lng": 106.461827
    },
    {
      "id": 1,
      "lat": 27.063337,
      "vehicle_card": "\u8d35AUA739",
      "lng": 106.958676
    },
    {
      "id": 1,
      "lat": 26.659589,
      "vehicle_card": "\u8d35AU3981",
      "lng": 106.743021
    },
    {
      "id": 1,
      "lat": 26.632811,
      "vehicle_card": "\u8d35AU5319",
      "lng": 106.759599
    },
    {
      "id": 1,
      "lat": 26.579895,
      "vehicle_card": "\u8d35AT1055",
      "lng": 106.665859
    },
    {
      "id": 1,
      "lat": 26.575552,
      "vehicle_card": "\u8d35AT1376",
      "lng": 106.686671
    },
    {
      "id": 1,
      "lat": 26.58445,
      "vehicle_card": "\u8d35A41086",
      "lng": 106.46992
    },
    {
      "id": 1,
      "lat": 26.572448,
      "vehicle_card": "\u8d35A78280",
      "lng": 106.650271
    },
    {
      "id": 1,
      "lat": 26.637853,
      "vehicle_card": "\u8d35A83232",
      "lng": 106.83442
    },
    {
      "id": 1,
      "lat": 27.059105,
      "vehicle_card": "\u8d35AUA738",
      "lng": 106.970119
    },
    {
      "id": 1,
      "lat": 26.757563,
      "vehicle_card": "\u8d35A38775",
      "lng": 106.350162
    },
    {
      "id": 1,
      "lat": 26.959853,
      "vehicle_card": "\u8d35A78191",
      "lng": 106.691661
    },
    {
      "id": 1,
      "lat": 26.685202,
      "vehicle_card": "\u8d35A157F1",
      "lng": 106.682104
    },
    {
      "id": 1,
      "lat": 26.58594,
      "vehicle_card": "\u8d35AT0547",
      "lng": 106.695049
    },
    {
      "id": 1,
      "lat": 26.361878,
      "vehicle_card": "\u8d35A61888",
      "lng": 106.683231
    },
    {
      "id": 1,
      "lat": 26.548642,
      "vehicle_card": "\u8d35AT1365",
      "lng": 106.79561
    },
    {
      "id": 1,
      "lat": 26.670004,
      "vehicle_card": "\u8d35A59454",
      "lng": 106.777807
    },
    {
      "id": 1,
      "lat": 26.616575,
      "vehicle_card": "\u8d35AT1369",
      "lng": 106.697879
    },
    {
      "id": 1,
      "lat": 26.575413,
      "vehicle_card": "\u8d35AT1106",
      "lng": 106.71016
    },
    {
      "id": 1,
      "lat": 26.361869,
      "vehicle_card": "\u8d35A66174",
      "lng": 106.683413
    },
    {
      "id": 1,
      "lat": 26.507023,
      "vehicle_card": "\u8d35AT1099",
      "lng": 106.670282
    },
    {
      "id": 1,
      "lat": 26.603871,
      "vehicle_card": "\u8d35AT1400",
      "lng": 106.640961
    },
    {
      "id": 1,
      "lat": 26.432331,
      "vehicle_card": "\u8d35AU3250",
      "lng": 106.662288
    },
    {
      "id": 1,
      "lat": 26.362149,
      "vehicle_card": "\u8d35A69045",
      "lng": 106.685685
    },
    {
      "id": 1,
      "lat": 27.079164,
      "vehicle_card": "\u8d35A43340",
      "lng": 106.74366
    },
    {
      "id": 1,
      "lat": 26.619544,
      "vehicle_card": "\u8d35AT1038",
      "lng": 106.732135
    },
    {
      "id": 1,
      "lat": 26.561599,
      "vehicle_card": "\u8d35AT1309",
      "lng": 106.724016
    },
    {
      "id": 1,
      "lat": 26.582439,
      "vehicle_card": "\u8d35AT1381",
      "lng": 106.664876
    },
    {
      "id": 1,
      "lat": 26.364366,
      "vehicle_card": "\u8d35AJK352",
      "lng": 106.682096
    },
    {
      "id": 1,
      "lat": 26.56968,
      "vehicle_card": "\u8d35AT2010",
      "lng": 106.698406
    },
    {
      "id": 1,
      "lat": 26.563731,
      "vehicle_card": "\u8d35AT1095",
      "lng": 106.655803
    },
    {
      "id": 1,
      "lat": 26.583315,
      "vehicle_card": "\u8d35AT1306",
      "lng": 106.638112
    },
    {
      "id": 1,
      "lat": 26.57985,
      "vehicle_card": "\u8d35AT1302",
      "lng": 106.665583
    },
    {
      "id": 1,
      "lat": 26.497055,
      "vehicle_card": "\u8d35A74306",
      "lng": 106.554733
    },
    {
      "id": 1,
      "lat": 26.636069,
      "vehicle_card": "\u8d35A57360",
      "lng": 106.356793
    },
    {
      "id": 1,
      "lat": 26.532205,
      "vehicle_card": "\u8d35A78408",
      "lng": 106.728172
    },
    {
      "id": 1,
      "lat": 26.585387,
      "vehicle_card": "\u8d35A35105",
      "lng": 106.631308
    },
    {
      "id": 1,
      "lat": 26.558035,
      "vehicle_card": "\u8d35A78199",
      "lng": 106.472238
    },
    {
      "id": 1,
      "lat": 26.605141,
      "vehicle_card": "\u8d35AU3897",
      "lng": 106.628014
    },
    {
      "id": 1,
      "lat": 26.362431,
      "vehicle_card": "\u8d35A69043",
      "lng": 106.680447
    },
    {
      "id": 1,
      "lat": 26.63831,
      "vehicle_card": "\u8d35A51022",
      "lng": 106.636658
    },
    {
      "id": 1,
      "lat": 26.743594,
      "vehicle_card": "\u8d35A41818",
      "lng": 106.355054
    },
    {
      "id": 1,
      "lat": 26.562105,
      "vehicle_card": "\u8d35A38772",
      "lng": 106.458309
    },
    {
      "id": 1,
      "lat": 26.636151,
      "vehicle_card": "\u8d35A3446P",
      "lng": 106.290771
    }
    ],
    "type": "freight_vehicle"
}