{
    "data":[
        {
      "id": 1,
      "lat": 26.627565,
      "vehicle_card": "\u8d35A77387",
      "lng": 106.6045
    },
    {
      "id": 1,
      "lat": 26.414417,
      "vehicle_card": "\u8d35A65513",
      "lng": 106.635169
    },
    {
      "id": 1,
      "lat": 26.585395,
      "vehicle_card": "\u8d35AU4391",
      "lng": 106.690994
    },
    {
      "id": 1,
      "lat": 26.386838,
      "vehicle_card": "\u8d35A60717",
      "lng": 106.69873
    },
    {
      "id": 1,
      "lat": 26.556106,
      "vehicle_card": "\u8d35A46130",
      "lng": 106.495506
    },
    {
      "id": 1,
      "lat": 26.651971,
      "vehicle_card": "\u8d35AU5388",
      "lng": 106.777211
    },
    {
      "id": 1,
      "lat": 26.561259,
      "vehicle_card": "\u8d35A48699",
      "lng": 106.460703
    },
    {
      "id": 1,
      "lat": 27.06586,
      "vehicle_card": "\u8d35A89753",
      "lng": 106.963142
    },
    {
      "id": 1,
      "lat": 26.840372,
      "vehicle_card": "\u8d35A37868",
      "lng": 106.703521
    },
    {
      "id": 1,
      "lat": 26.576978,
      "vehicle_card": "\u8d35AU5322",
      "lng": 106.701344
    },
    {
      "id": 1,
      "lat": 26.6004,
      "vehicle_card": "\u8d35AU5377",
      "lng": 106.715865
    },
    {
      "id": 1,
      "lat": 26.408579,
      "vehicle_card": "\u8d35A46816",
      "lng": 106.597633
    },
    {
      "id": 1,
      "lat": 26.44724,
      "vehicle_card": "\u8d35A49420",
      "lng": 106.737251
    },
    {
      "id": 1,
      "lat": 26.381716,
      "vehicle_card": "\u8d35A55406",
      "lng": 106.677064
    },
    {
      "id": 1,
      "lat": 26.704583,
      "vehicle_card": "\u8d35AA9691",
      "lng": 106.653381
    },
    {
      "id": 1,
      "lat": 26.635211,
      "vehicle_card": "\u8d35AU5396",
      "lng": 106.76486
    },
    {
      "id": 1,
      "lat": 26.6589,
      "vehicle_card": "\u8d35AU3780",
      "lng": 106.55435
    },
    {
      "id": 1,
      "lat": 26.588699,
      "vehicle_card": "\u8d35A57601",
      "lng": 106.504455
    },
    {
      "id": 1,
      "lat": 26.483753,
      "vehicle_card": "\u8d35A62071",
      "lng": 106.735901
    },
    {
      "id": 1,
      "lat": 26.888847,
      "vehicle_card": "\u8d35AT1171",
      "lng": 107.055815
    },
    {
      "id": 1,
      "lat": 26.564276,
      "vehicle_card": "\u8d35AAB671",
      "lng": 106.475381
    },
    {
      "id": 1,
      "lat": 27.011417,
      "vehicle_card": "\u8d35A48476",
      "lng": 106.923512
    },
    {
      "id": 1,
      "lat": 26.583165,
      "vehicle_card": "\u8d35A41062",
      "lng": 106.466818
    },
    {
      "id": 1,
      "lat": 26.603575,
      "vehicle_card": "\u8d35AU3920",
      "lng": 106.7148
    },
    {
      "id": 1,
      "lat": 27.056639,
      "vehicle_card": "\u8d35AUA757",
      "lng": 106.973813
    },
    {
      "id": 1,
      "lat": 26.68542,
      "vehicle_card": "\u8d35A51017",
      "lng": 106.625696
    },
    {
      "id": 1,
      "lat": 26.684591,
      "vehicle_card": "\u8d35AU4572",
      "lng": 106.630053
    },
    {
      "id": 1,
      "lat": 26.55798,
      "vehicle_card": "\u8d35A78197",
      "lng": 106.472053
    },
    {
      "id": 1,
      "lat": 26.589919,
      "vehicle_card": "\u8d35AU5329",
      "lng": 106.715391
    },
    {
      "id": 1,
      "lat": 26.6006,
      "vehicle_card": "\u8d35AU9936",
      "lng": 106.714078
    },
    {
      "id": 1,
      "lat": 27.067307,
      "vehicle_card": "\u8d35AA1592",
      "lng": 106.965363
    },
    {
      "id": 1,
      "lat": 26.633858,
      "vehicle_card": "\u8d35AU3986",
      "lng": 106.76207
    },
    {
      "id": 1,
      "lat": 26.629172,
      "vehicle_card": "\u8d35A48686",
      "lng": 106.36141
    },
    {
      "id": 1,
      "lat": 26.459556,
      "vehicle_card": "\u8d35A593K1",
      "lng": 106.734603
    },
    {
      "id": 1,
      "lat": 26.527986,
      "vehicle_card": "\u8d35AT2289",
      "lng": 106.708679
    },
    {
      "id": 1,
      "lat": 26.562983,
      "vehicle_card": "\u8d35AD0061",
      "lng": 106.475787
    },
    {
      "id": 1,
      "lat": 26.998583,
      "vehicle_card": "\u8d35A72855",
      "lng": 106.904816
    },
    {
      "id": 1,
      "lat": 26.842692,
      "vehicle_card": "\u8d35A65628",
      "lng": 106.597363
    },
    {
      "id": 1,
      "lat": 26.551287,
      "vehicle_card": "\u8d35A57181",
      "lng": 106.45392
    },
    {
      "id": 1,
      "lat": 26.56099,
      "vehicle_card": "\u8d35A41060",
      "lng": 106.447772
    },
    {
      "id": 1,
      "lat": 27.091545,
      "vehicle_card": "\u8d35A35994",
      "lng": 106.988616
    },
    {
      "id": 1,
      "lat": 26.55965,
      "vehicle_card": "\u8d35A88413",
      "lng": 106.610016
    },
    {
      "id": 1,
      "lat": 26.585727,
      "vehicle_card": "\u8d35A41099",
      "lng": 106.688255
    },
    {
      "id": 1,
      "lat": 26.597122,
      "vehicle_card": "\u8d35A38732",
      "lng": 106.577522
    },
    {
      "id": 1,
      "lat": 26.38319,
      "vehicle_card": "\u8d35A38431",
      "lng": 106.676498
    },
    {
      "id": 1,
      "lat": 27.16267,
      "vehicle_card": "\u8d35A72865",
      "lng": 106.723495
    },
    {
      "id": 1,
      "lat": 27.065732,
      "vehicle_card": "\u8d35A41823",
      "lng": 106.963607
    },
    {
      "id": 1,
      "lat": 26.600793,
      "vehicle_card": "\u8d35A686E6",
      "lng": 106.655586
    },
    {
      "id": 1,
      "lat": 27.046951,
      "vehicle_card": "\u8d35A57327",
      "lng": 107.012817
    },
    {
      "id": 1,
      "lat": 26.487064,
      "vehicle_card": "\u8d35AT1805",
      "lng": 106.627235
    },
    {
      "id": 1,
      "lat": 26.846415,
      "vehicle_card": "\u8d35A72676",
      "lng": 106.594924
    },
    {
      "id": 1,
      "lat": 26.881109,
      "vehicle_card": "\u8d35A57410",
      "lng": 107.101783
    },
    {
      "id": 1,
      "lat": 26.539453,
      "vehicle_card": "\u8d35AP9628",
      "lng": 106.483531
    },
    {
      "id": 1,
      "lat": 27.151084,
      "vehicle_card": "\u8d35A72864",
      "lng": 106.717681
    },
    {
      "id": 1,
      "lat": 26.598974,
      "vehicle_card": "\u8d35A25035",
      "lng": 106.57785
    },
    {
      "id": 1,
      "lat": 26.586702,
      "vehicle_card": "\u8d35AT5138",
      "lng": 106.694953
    },
    {
      "id": 1,
      "lat": 26.64472,
      "vehicle_card": "\u8d35AT0046",
      "lng": 106.66456
    },
    {
      "id": 1,
      "lat": 26.489442,
      "vehicle_card": "\u8d35A68995",
      "lng": 106.611022
    },
    {
      "id": 1,
      "lat": 26.666691,
      "vehicle_card": "\u8d35AU3998",
      "lng": 106.808211
    },
    {
      "id": 1,
      "lat": 26.576474,
      "vehicle_card": "\u8d35A38702",
      "lng": 106.441203
    },
    {
      "id": 1,
      "lat": 26.646945,
      "vehicle_card": "\u8d35A49558",
      "lng": 106.752906
    },
    {
      "id": 1,
      "lat": 26.581197,
      "vehicle_card": "\u8d35A74611",
      "lng": 106.641395
    },
    {
      "id": 1,
      "lat": 26.448806,
      "vehicle_card": "\u8d35A74693",
      "lng": 106.737358
    },
    {
      "id": 1,
      "lat": 27.122032,
      "vehicle_card": "\u8d35A80947",
      "lng": 106.910369
    },
    {
      "id": 1,
      "lat": 27.065718,
      "vehicle_card": "\u8d35A58463",
      "lng": 106.965216
    },
    {
      "id": 1,
      "lat": 26.545911,
      "vehicle_card": "\u8d35A82870",
      "lng": 106.48239
    },
    {
      "id": 1,
      "lat": 26.532461,
      "vehicle_card": "\u8d35AT1762",
      "lng": 106.706451
    },
    {
      "id": 1,
      "lat": 27.065746,
      "vehicle_card": "\u8d35A65418",
      "lng": 106.963157
    },
    {
      "id": 1,
      "lat": 26.624887,
      "vehicle_card": "\u8d35AT1575",
      "lng": 106.633338
    },
    {
      "id": 1,
      "lat": 26.858041,
      "vehicle_card": "\u8d35A74602",
      "lng": 106.737808
    },
    {
      "id": 1,
      "lat": 26.935979,
      "vehicle_card": "\u8d35A21682",
      "lng": 106.69622
    },
    {
      "id": 1,
      "lat": 26.789256,
      "vehicle_card": "\u8d35A46174",
      "lng": 107.020237
    },
    {
      "id": 1,
      "lat": 26.684916,
      "vehicle_card": "\u8d35A77388",
      "lng": 106.63012
    },
    {
      "id": 1,
      "lat": 26.607696,
      "vehicle_card": "\u8d35A56581",
      "lng": 106.36663
    },
    {
      "id": 1,
      "lat": 26.570599,
      "vehicle_card": "\u8d35AT0397",
      "lng": 106.7262
    },
    {
      "id": 1,
      "lat": 27.03311,
      "vehicle_card": "\u8d35A649H3",
      "lng": 106.712003
    },
    {
      "id": 1,
      "lat": 26.60741,
      "vehicle_card": "\u8d35AT2166",
      "lng": 106.759284
    },
    {
      "id": 1,
      "lat": 27.073725,
      "vehicle_card": "\u8d35A83183",
      "lng": 106.991796
    },
    {
      "id": 1,
      "lat": 26.596683,
      "vehicle_card": "\u8d35AT5259",
      "lng": 106.654464
    },
    {
      "id": 1,
      "lat": 26.649575,
      "vehicle_card": "\u8d35AT0353",
      "lng": 106.640507
    },
    {
      "id": 1,
      "lat": 27.079656,
      "vehicle_card": "\u8d35AA8670",
      "lng": 106.742134
    },
    {
      "id": 1,
      "lat": 26.49006,
      "vehicle_card": "\u8d35AU4827",
      "lng": 106.670308
    },
    {
      "id": 1,
      "lat": 26.667581,
      "vehicle_card": "\u8d35AU5650",
      "lng": 106.657551
    },
    {
      "id": 1,
      "lat": 26.483947,
      "vehicle_card": "\u8d35A37983",
      "lng": 106.73626
    },
    {
      "id": 1,
      "lat": 26.577508,
      "vehicle_card": "\u8d35A38701",
      "lng": 106.556929
    },
    {
      "id": 1,
      "lat": 26.557561,
      "vehicle_card": "\u8d35A60636",
      "lng": 106.460983
    },
    {
      "id": 1,
      "lat": 26.579797,
      "vehicle_card": "\u8d35AT1462",
      "lng": 106.665679
    },
    {
      "id": 1,
      "lat": 26.56297,
      "vehicle_card": "\u8d35AT1459",
      "lng": 106.448068
    },
    {
      "id": 1,
      "lat": 26.490817,
      "vehicle_card": "\u8d35ALM118",
      "lng": 106.736198
    },
    {
      "id": 1,
      "lat": 26.829355,
      "vehicle_card": "\u8d35A678M2",
      "lng": 106.589925
    },
    {
      "id": 1,
      "lat": 26.838616,
      "vehicle_card": "\u8d35AU4186",
      "lng": 106.594906
    },
    {
      "id": 1,
      "lat": 26.682197,
      "vehicle_card": "\u8d35AT1526",
      "lng": 106.624031
    },
    {
      "id": 1,
      "lat": 27.101288,
      "vehicle_card": "\u8d35A64723",
      "lng": 106.731103
    },
    {
      "id": 1,
      "lat": 26.361865,
      "vehicle_card": "\u8d35A51695",
      "lng": 106.683711
    },
    {
      "id": 1,
      "lat": 26.647232,
      "vehicle_card": "\u8d35AT1759",
      "lng": 106.752532
    },
    {
      "id": 1,
      "lat": 26.531585,
      "vehicle_card": "\u8d35AT1629",
      "lng": 106.784408
    },
    {
      "id": 1,
      "lat": 26.695486,
      "vehicle_card": "\u8d35AU4588",
      "lng": 106.622228
    },
    {
      "id": 1,
      "lat": 27.065833,
      "vehicle_card": "\u8d35A67904",
      "lng": 106.96508
    },
    {
      "id": 1,
      "lat": 26.462057,
      "vehicle_card": "\u8d35A43998",
      "lng": 106.706565
    },
    {
      "id": 1,
      "lat": 26.540975,
      "vehicle_card": "\u8d35A89814",
      "lng": 106.47847
    },
    {
      "id": 1,
      "lat": 26.462317,
      "vehicle_card": "\u8d35A55404",
      "lng": 106.645234
    },
    {
      "id": 1,
      "lat": 26.586145,
      "vehicle_card": "\u8d35A78206",
      "lng": 106.695652
    },
    {
      "id": 1,
      "lat": 27.05792,
      "vehicle_card": "\u8d35AU9836",
      "lng": 106.982862
    },
    {
      "id": 1,
      "lat": 26.440322,
      "vehicle_card": "\u8d35A62510",
      "lng": 106.673225
    },
    {
      "id": 1,
      "lat": 26.520095,
      "vehicle_card": "\u8d35AT0325",
      "lng": 106.769905
    },
    {
      "id": 1,
      "lat": 26.591423,
      "vehicle_card": "\u8d35AU3911",
      "lng": 106.468936
    },
    {
      "id": 1,
      "lat": 26.475597,
      "vehicle_card": "\u8d35A87234",
      "lng": 106.659043
    },
    {
      "id": 1,
      "lat": 26.644123,
      "vehicle_card": "\u8d35A54911",
      "lng": 106.800491
    },
    {
      "id": 1,
      "lat": 26.616699,
      "vehicle_card": "\u8d35AT2131",
      "lng": 106.697807
    },
    {
      "id": 1,
      "lat": 27.171089,
      "vehicle_card": "\u8d35A65862",
      "lng": 106.7227
    },
    {
      "id": 1,
      "lat": 26.583017,
      "vehicle_card": "\u8d35A88415",
      "lng": 106.641519
    },
    {
      "id": 1,
      "lat": 27.066822,
      "vehicle_card": "\u8d35AUA753",
      "lng": 106.947274
    },
    {
      "id": 1,
      "lat": 26.613048,
      "vehicle_card": "\u8d35AT0388",
      "lng": 106.691473
    },
    {
      "id": 1,
      "lat": 26.83886,
      "vehicle_card": "\u8d35AA9983",
      "lng": 106.595188
    },
    {
      "id": 1,
      "lat": 26.568054,
      "vehicle_card": "\u8d35AT2006",
      "lng": 106.749377
    },
    {
      "id": 1,
      "lat": 26.53087,
      "vehicle_card": "\u8d35AT1623",
      "lng": 106.784216
    },
    {
      "id": 1,
      "lat": 26.580119,
      "vehicle_card": "\u8d35AT8555",
      "lng": 106.665798
    },
    {
      "id": 1,
      "lat": 26.530561,
      "vehicle_card": "\u8d35AT0022",
      "lng": 106.7846
    },
    {
      "id": 1,
      "lat": 26.450775,
      "vehicle_card": "\u8d35AFX298",
      "lng": 106.722883
    },
    {
      "id": 1,
      "lat": 26.552765,
      "vehicle_card": "\u8d35AU3906",
      "lng": 106.457925
    },
    {
      "id": 1,
      "lat": 26.560164,
      "vehicle_card": "\u8d35AU9372",
      "lng": 106.463408
    },
    {
      "id": 1,
      "lat": 26.702685,
      "vehicle_card": "\u8d35A60974",
      "lng": 106.651533
    },
    {
      "id": 1,
      "lat": 26.626938,
      "vehicle_card": "\u8d35A996M6",
      "lng": 106.578764
    },
    {
      "id": 1,
      "lat": 26.93486,
      "vehicle_card": "\u8d35A45330",
      "lng": 106.700332
    },
    {
      "id": 1,
      "lat": 26.548899,
      "vehicle_card": "\u8d35AA1864",
      "lng": 106.456418
    },
    {
      "id": 1,
      "lat": 26.628352,
      "vehicle_card": "\u8d35A64991",
      "lng": 106.333239
    },
    {
      "id": 1,
      "lat": 26.848409,
      "vehicle_card": "\u8d35A971F6",
      "lng": 106.613177
    },
    {
      "id": 1,
      "lat": 26.587363,
      "vehicle_card": "\u8d35AA4875",
      "lng": 106.477483
    },
    {
      "id": 1,
      "lat": 26.588165,
      "vehicle_card": "\u8d35A6041S",
      "lng": 106.368471
    },
    {
      "id": 1,
      "lat": 26.554983,
      "vehicle_card": "\u8d35AU9815",
      "lng": 106.459355
    },
    {
      "id": 1,
      "lat": 26.736231,
      "vehicle_card": "\u8d35A77067",
      "lng": 106.805
    },
    {
      "id": 1,
      "lat": 26.565043,
      "vehicle_card": "\u8d35A60603",
      "lng": 106.47302
    },
    {
      "id": 1,
      "lat": 26.621536,
      "vehicle_card": "\u8d35A77290",
      "lng": 106.608823
    },
    {
      "id": 1,
      "lat": 26.545227,
      "vehicle_card": "\u8d35AT1598",
      "lng": 106.704559
    },
    {
      "id": 1,
      "lat": 26.486816,
      "vehicle_card": "\u8d35AT1754",
      "lng": 106.625534
    },
    {
      "id": 1,
      "lat": 26.405229,
      "vehicle_card": "\u8d35A62194",
      "lng": 106.667572
    },
    {
      "id": 1,
      "lat": 26.58358,
      "vehicle_card": "\u8d35AT2279",
      "lng": 106.66481
    },
    {
      "id": 1,
      "lat": 27.099453,
      "vehicle_card": "\u8d35A65853",
      "lng": 106.731086
    },
    {
      "id": 1,
      "lat": 27.058315,
      "vehicle_card": "\u8d35AUA742",
      "lng": 106.965989
    },
    {
      "id": 1,
      "lat": 26.43965,
      "vehicle_card": "\u8d35AU3256",
      "lng": 106.671216
    },
    {
      "id": 1,
      "lat": 26.599173,
      "vehicle_card": "\u8d35AT1235",
      "lng": 106.730925
    },
    {
      "id": 1,
      "lat": 26.561911,
      "vehicle_card": "\u8d35AU3933",
      "lng": 106.461805
    },
    {
      "id": 1,
      "lat": 26.687799,
      "vehicle_card": "\u8d35A58418",
      "lng": 106.521864
    },
    {
      "id": 1,
      "lat": 27.095771,
      "vehicle_card": "\u8d35A071C6",
      "lng": 106.741821
    },
    {
      "id": 1,
      "lat": 26.600629,
      "vehicle_card": "\u8d35A7123.",
      "lng": 106.6557
    },
    {
      "id": 1,
      "lat": 27.062716,
      "vehicle_card": "\u8d35AU9906",
      "lng": 106.957906
    },
    {
      "id": 1,
      "lat": 26.682802,
      "vehicle_card": "\u8d35AT5188",
      "lng": 106.705295
    },
    {
      "id": 1,
      "lat": 26.532529,
      "vehicle_card": "\u8d35AT0939",
      "lng": 106.706207
    },
    {
      "id": 1,
      "lat": 26.680492,
      "vehicle_card": "\u8d35A43971",
      "lng": 106.614738
    },
    {
      "id": 1,
      "lat": 26.588855,
      "vehicle_card": "\u8d35AT0654",
      "lng": 106.739952
    },
    {
      "id": 1,
      "lat": 26.575884,
      "vehicle_card": "\u8d35AT1051",
      "lng": 106.688251
    },
    {
      "id": 1,
      "lat": 26.978709,
      "vehicle_card": "\u8d35AT0955",
      "lng": 106.439638
    },
    {
      "id": 1,
      "lat": 26.848501,
      "vehicle_card": "\u8d35A542A2",
      "lng": 106.613018
    },
    {
      "id": 1,
      "lat": 26.438195,
      "vehicle_card": "\u8d35AT1265",
      "lng": 106.724022
    },
    {
      "id": 1,
      "lat": 26.938565,
      "vehicle_card": "\u8d35A79968",
      "lng": 106.833996
    },
    {
      "id": 1,
      "lat": 26.529716,
      "vehicle_card": "\u8d35A88411",
      "lng": 106.588911
    },
    {
      "id": 1,
      "lat": 26.654588,
      "vehicle_card": "\u8d35A3151Z",
      "lng": 106.659973
    },
    {
      "id": 1,
      "lat": 27.106071,
      "vehicle_card": "\u8d35A381L1",
      "lng": 106.73073
    },
    {
      "id": 1,
      "lat": 27.055121,
      "vehicle_card": "\u8d35A47284",
      "lng": 106.851447
    },
    {
      "id": 1,
      "lat": 26.695123,
      "vehicle_card": "\u8d35A751B3",
      "lng": 106.62741
    },
    {
      "id": 1,
      "lat": 26.594029,
      "vehicle_card": "\u8d35AT1025",
      "lng": 106.669097
    },
    {
      "id": 1,
      "lat": 26.636891,
      "vehicle_card": "\u8d35AU6618",
      "lng": 106.768204
    },
    {
      "id": 1,
      "lat": 26.473315,
      "vehicle_card": "\u8d35A48222",
      "lng": 106.741738
    },
    {
      "id": 1,
      "lat": 26.776135,
      "vehicle_card": "\u8d35A717F7",
      "lng": 106.747605
    },
    {
      "id": 1,
      "lat": 26.554885,
      "vehicle_card": "\u8d35A34968",
      "lng": 106.710884
    },
    {
      "id": 1,
      "lat": 26.459645,
      "vehicle_card": "\u8d35AJM579",
      "lng": 106.734435
    },
    {
      "id": 1,
      "lat": 26.556938,
      "vehicle_card": "\u8d35AU6050",
      "lng": 106.459305
    },
    {
      "id": 1,
      "lat": 26.649086,
      "vehicle_card": "\u8d35A601A8",
      "lng": 106.784891
    },
    {
      "id": 1,
      "lat": 26.979931,
      "vehicle_card": "\u8d35A54947",
      "lng": 106.558995
    },
    {
      "id": 1,
      "lat": 26.53124,
      "vehicle_card": "\u8d35AT1643",
      "lng": 106.784529
    },
    {
      "id": 1,
      "lat": 27.138105,
      "vehicle_card": "\u8d35AA2881",
      "lng": 106.913871
    },
    {
      "id": 1,
      "lat": 26.599407,
      "vehicle_card": "\u8d35A01233",
      "lng": 106.575897
    },
    {
      "id": 1,
      "lat": 26.640159,
      "vehicle_card": "\u8d35A35971",
      "lng": 106.303009
    },
    {
      "id": 1,
      "lat": 27.114952,
      "vehicle_card": "\u8d35AA4833",
      "lng": 106.843734
    },
    {
      "id": 1,
      "lat": 26.567483,
      "vehicle_card": "\u8d35A41069",
      "lng": 106.444635
    },
    {
      "id": 1,
      "lat": 27.079528,
      "vehicle_card": "\u8d35A77521",
      "lng": 106.743927
    },
    {
      "id": 1,
      "lat": 27.232166,
      "vehicle_card": "\u8d35A56368",
      "lng": 106.978614
    },
    {
      "id": 1,
      "lat": 27.065664,
      "vehicle_card": "\u8d35A54871",
      "lng": 106.964134
    },
    {
      "id": 1,
      "lat": 27.06569,
      "vehicle_card": "\u8d35A54866",
      "lng": 106.964958
    },
    {
      "id": 1,
      "lat": 26.59889,
      "vehicle_card": "\u8d35A35242",
      "lng": 106.575913
    },
    {
      "id": 1,
      "lat": 26.598755,
      "vehicle_card": "\u8d35A49520",
      "lng": 106.575898
    },
    {
      "id": 1,
      "lat": 27.114861,
      "vehicle_card": "\u8d35A54228",
      "lng": 106.843343
    },
    {
      "id": 1,
      "lat": 27.056065,
      "vehicle_card": "\u8d35A55571",
      "lng": 106.973738
    },
    {
      "id": 1,
      "lat": 26.558092,
      "vehicle_card": "\u8d35A29831",
      "lng": 106.472602
    },
    {
      "id": 1,
      "lat": 26.524192,
      "vehicle_card": "\u8d35A64775",
      "lng": 106.772041
    },
    {
      "id": 1,
      "lat": 27.137771,
      "vehicle_card": "\u8d35A46191",
      "lng": 106.913902
    },
    {
      "id": 1,
      "lat": 27.079418,
      "vehicle_card": "\u8d35A77243",
      "lng": 106.743621
    },
    {
      "id": 1,
      "lat": 27.093375,
      "vehicle_card": "\u8d35AU9356",
      "lng": 106.965843
    },
    {
      "id": 1,
      "lat": 26.554885,
      "vehicle_card": "\u8d35AU4843",
      "lng": 106.685623
    },
    {
      "id": 1,
      "lat": 27.096048,
      "vehicle_card": "\u8d35AA1651",
      "lng": 106.727737
    },
    {
      "id": 1,
      "lat": 26.59822,
      "vehicle_card": "\u8d35A48065",
      "lng": 106.576148
    },
    {
      "id": 1,
      "lat": 27.068136,
      "vehicle_card": "\u8d35AU8873",
      "lng": 106.967933
    },
    {
      "id": 1,
      "lat": 27.0118,
      "vehicle_card": "\u8d35A88768",
      "lng": 106.596542
    },
    {
      "id": 1,
      "lat": 27.114885,
      "vehicle_card": "\u8d35A43766",
      "lng": 106.843681
    },
    {
      "id": 1,
      "lat": 27.096832,
      "vehicle_card": "\u8d35A54618",
      "lng": 106.726196
    },
    {
      "id": 1,
      "lat": 26.601369,
      "vehicle_card": "\u8d35A71842",
      "lng": 106.581809
    },
    {
      "id": 1,
      "lat": 26.59959,
      "vehicle_card": "\u8d35A40008",
      "lng": 106.575599
    },
    {
      "id": 1,
      "lat": 26.578279,
      "vehicle_card": "\u8d35A81589",
      "lng": 106.567626
    },
    {
      "id": 1,
      "lat": 26.599512,
      "vehicle_card": "\u8d35A32260",
      "lng": 106.576934
    },
    {
      "id": 1,
      "lat": 26.718826,
      "vehicle_card": "\u8d35A01566",
      "lng": 106.570823
    },
    {
      "id": 1,
      "lat": 26.598834,
      "vehicle_card": "\u8d35A52322",
      "lng": 106.577163
    },
    {
      "id": 1,
      "lat": 26.825607,
      "vehicle_card": "\u8d35A88879",
      "lng": 106.705848
    },
    {
      "id": 1,
      "lat": 26.51219,
      "vehicle_card": "\u8d35A709L0",
      "lng": 106.675947
    },
    {
      "id": 1,
      "lat": 27.059958,
      "vehicle_card": "\u8d35A74702",
      "lng": 106.856681
    },
    {
      "id": 1,
      "lat": 26.571226,
      "vehicle_card": "\u8d35A48700",
      "lng": 106.442202
    },
    {
      "id": 1,
      "lat": 26.726096,
      "vehicle_card": "\u8d35A71737",
      "lng": 106.36022
    },
    {
      "id": 1,
      "lat": 26.572374,
      "vehicle_card": "\u8d35AT5333",
      "lng": 106.72576
    },
    {
      "id": 1,
      "lat": 26.814384,
      "vehicle_card": "\u8d35AU4189",
      "lng": 106.595343
    },
    {
      "id": 1,
      "lat": 26.752665,
      "vehicle_card": "\u8d35A69643",
      "lng": 106.689259
    },
    {
      "id": 1,
      "lat": 26.88521,
      "vehicle_card": "\u8d35A69096",
      "lng": 107.09497
    },
    {
      "id": 1,
      "lat": 26.62441,
      "vehicle_card": "\u8d35A09N70",
      "lng": 106.732528
    },
    {
      "id": 1,
      "lat": 26.546922,
      "vehicle_card": "\u8d35A53272",
      "lng": 106.459884
    },
    {
      "id": 1,
      "lat": 26.56422,
      "vehicle_card": "\u8d35A53292",
      "lng": 106.490371
    },
    {
      "id": 1,
      "lat": 27.121801,
      "vehicle_card": "\u8d35A59668",
      "lng": 106.910278
    },
    {
      "id": 1,
      "lat": 26.583837,
      "vehicle_card": "\u8d35A31782",
      "lng": 106.641761
    },
    {
      "id": 1,
      "lat": 26.451946,
      "vehicle_card": "\u8d35A74092",
      "lng": 106.735557
    },
    {
      "id": 1,
      "lat": 26.580984,
      "vehicle_card": "\u8d35A36721",
      "lng": 106.640113
    },
    {
      "id": 1,
      "lat": 26.452814,
      "vehicle_card": "\u8d35A85068",
      "lng": 106.741744
    },
    {
      "id": 1,
      "lat": 27.133977,
      "vehicle_card": "\u8d35A57097",
      "lng": 106.913665
    },
    {
      "id": 1,
      "lat": 26.716251,
      "vehicle_card": "\u8d35A74695",
      "lng": 106.674728
    },
    {
      "id": 1,
      "lat": 26.469749,
      "vehicle_card": "\u8d35A36906",
      "lng": 106.61293
    },
    {
      "id": 1,
      "lat": 26.530315,
      "vehicle_card": "\u8d35A77507",
      "lng": 106.82698
    },
    {
      "id": 1,
      "lat": 26.487762,
      "vehicle_card": "\u8d35A68996",
      "lng": 106.641838
    },
    {
      "id": 1,
      "lat": 27.134105,
      "vehicle_card": "\u8d35A59669",
      "lng": 106.914299
    },
    {
      "id": 1,
      "lat": 26.447332,
      "vehicle_card": "\u8d35A49449",
      "lng": 106.73748
    },
    {
      "id": 1,
      "lat": 27.1224,
      "vehicle_card": "\u8d35A80980",
      "lng": 106.910575
    },
    {
      "id": 1,
      "lat": 26.857852,
      "vehicle_card": "\u8d35A31792",
      "lng": 106.737983
    },
    {
      "id": 1,
      "lat": 27.122493,
      "vehicle_card": "\u8d35A80849",
      "lng": 106.910629
    },
    {
      "id": 1,
      "lat": 26.457077,
      "vehicle_card": "\u8d35A51100",
      "lng": 106.741806
    },
    {
      "id": 1,
      "lat": 26.452518,
      "vehicle_card": "\u8d35A28947",
      "lng": 106.736679
    },
    {
      "id": 1,
      "lat": 27.133499,
      "vehicle_card": "\u8d35A57688",
      "lng": 106.913482
    },
    {
      "id": 1,
      "lat": 27.122098,
      "vehicle_card": "\u8d35A80895",
      "lng": 106.910461
    },
    {
      "id": 1,
      "lat": 26.54047,
      "vehicle_card": "\u8d35A63416",
      "lng": 106.726844
    },
    {
      "id": 1,
      "lat": 27.111467,
      "vehicle_card": "\u8d35A57111",
      "lng": 106.910331
    },
    {
      "id": 1,
      "lat": 26.448291,
      "vehicle_card": "\u8d35A87108",
      "lng": 106.737083
    },
    {
      "id": 1,
      "lat": 26.581422,
      "vehicle_card": "\u8d35A53257",
      "lng": 106.579513
    },
    {
      "id": 1,
      "lat": 26.792829,
      "vehicle_card": "\u8d35A64429",
      "lng": 106.615959
    },
    {
      "id": 1,
      "lat": 26.581504,
      "vehicle_card": "\u8d35A67195",
      "lng": 106.640464
    },
    {
      "id": 1,
      "lat": 26.546207,
      "vehicle_card": "\u8d35A58053",
      "lng": 106.696998
    },
    {
      "id": 1,
      "lat": 26.451274,
      "vehicle_card": "\u8d35A74747",
      "lng": 106.742759
    },
    {
      "id": 1,
      "lat": 26.489538,
      "vehicle_card": "\u8d35A68993",
      "lng": 106.611221
    },
    {
      "id": 1,
      "lat": 26.580297,
      "vehicle_card": "\u8d35A42007",
      "lng": 106.640075
    },
    {
      "id": 1,
      "lat": 26.55006,
      "vehicle_card": "\u8d35A40578",
      "lng": 106.471916
    },
    {
      "id": 1,
      "lat": 26.563192,
      "vehicle_card": "\u8d35A50222",
      "lng": 106.488395
    },
    {
      "id": 1,
      "lat": 27.071603,
      "vehicle_card": "\u8d35A57108",
      "lng": 106.970977
    },
    {
      "id": 1,
      "lat": 27.122499,
      "vehicle_card": "\u8d35A57110",
      "lng": 106.910522
    },
    {
      "id": 1,
      "lat": 26.736978,
      "vehicle_card": "\u8d35A71637",
      "lng": 106.681037
    },
    {
      "id": 1,
      "lat": 26.436887,
      "vehicle_card": "\u8d35A62509",
      "lng": 106.674232
    },
    {
      "id": 1,
      "lat": 26.367326,
      "vehicle_card": "\u8d35A62416",
      "lng": 106.681449
    },
    {
      "id": 1,
      "lat": 26.367332,
      "vehicle_card": "\u8d35A62422",
      "lng": 106.681457
    },
    {
      "id": 1,
      "lat": 26.578805,
      "vehicle_card": "\u8d35A84101",
      "lng": 106.639533
    },
    {
      "id": 1,
      "lat": 26.419506,
      "vehicle_card": "\u8d35A57259",
      "lng": 106.652565
    },
    {
      "id": 1,
      "lat": 26.421037,
      "vehicle_card": "\u8d35A62344",
      "lng": 106.673095
    },
    {
      "id": 1,
      "lat": 26.440212,
      "vehicle_card": "\u8d35A57332",
      "lng": 106.673965
    },
    {
      "id": 1,
      "lat": 26.379043,
      "vehicle_card": "\u8d35A62413",
      "lng": 106.673591
    },
    {
      "id": 1,
      "lat": 26.43823,
      "vehicle_card": "\u8d35A57338",
      "lng": 106.673904
    },
    {
      "id": 1,
      "lat": 26.600727,
      "vehicle_card": "\u8d35A11N26",
      "lng": 106.655838
    },
    {
      "id": 1,
      "lat": 26.621923,
      "vehicle_card": "\u8d35A1174V",
      "lng": 106.641273
    },
    {
      "id": 1,
      "lat": 26.417575,
      "vehicle_card": "\u8d35A62604",
      "lng": 106.649055
    },
    {
      "id": 1,
      "lat": 26.43976,
      "vehicle_card": "\u8d35A60660",
      "lng": 106.67395
    },
    {
      "id": 1,
      "lat": 26.409322,
      "vehicle_card": "\u8d35A60712",
      "lng": 106.597846
    },
    {
      "id": 1,
      "lat": 26.481191,
      "vehicle_card": "\u8d35A57240",
      "lng": 106.58815
    },
    {
      "id": 1,
      "lat": 26.366392,
      "vehicle_card": "\u8d35A57266",
      "lng": 106.663444
    },
    {
      "id": 1,
      "lat": 27.045471,
      "vehicle_card": "\u8d35A1134V",
      "lng": 106.970176
    },
    {
      "id": 1,
      "lat": 26.442422,
      "vehicle_card": "\u8d35A62511",
      "lng": 106.67337
    },
    {
      "id": 1,
      "lat": 26.503223,
      "vehicle_card": "\u8d35A60705",
      "lng": 106.672859
    },
    {
      "id": 1,
      "lat": 26.441341,
      "vehicle_card": "\u8d35A60697",
      "lng": 106.673393
    },
    {
      "id": 1,
      "lat": 26.426691,
      "vehicle_card": "\u8d35A62425",
      "lng": 106.674232
    },
    {
      "id": 1,
      "lat": 26.417028,
      "vehicle_card": "\u8d35A57261",
      "lng": 106.646415
    },
    {
      "id": 1,
      "lat": 26.423702,
      "vehicle_card": "\u8d35A62421",
      "lng": 106.673645
    },
    {
      "id": 1,
      "lat": 26.480775,
      "vehicle_card": "\u8d35A82388",
      "lng": 106.504951
    },
    {
      "id": 1,
      "lat": 26.568548,
      "vehicle_card": "\u8d35A20Z10",
      "lng": 106.730026
    },
    {
      "id": 1,
      "lat": 26.4925,
      "vehicle_card": "\u8d35A60699",
      "lng": 106.670867
    },
    {
      "id": 1,
      "lat": 26.934249,
      "vehicle_card": "\u8d35A5KB78",
      "lng": 106.964721
    },
    {
      "id": 1,
      "lat": 26.442466,
      "vehicle_card": "\u8d35A62418",
      "lng": 106.673355
    },
    {
      "id": 1,
      "lat": 26.450756,
      "vehicle_card": "\u8d35A60693",
      "lng": 106.672851
    },
    {
      "id": 1,
      "lat": 26.432273,
      "vehicle_card": "\u8d35A57267",
      "lng": 106.664962
    },
    {
      "id": 1,
      "lat": 26.386993,
      "vehicle_card": "\u8d35A60706",
      "lng": 106.675697
    },
    {
      "id": 1,
      "lat": 26.498916,
      "vehicle_card": "\u8d35A58134",
      "lng": 106.650047
    },
    {
      "id": 1,
      "lat": 26.432107,
      "vehicle_card": "\u8d35A60701",
      "lng": 106.673919
    },
    {
      "id": 1,
      "lat": 26.440177,
      "vehicle_card": "\u8d35A62409",
      "lng": 106.673965
    },
    {
      "id": 1,
      "lat": 26.44012,
      "vehicle_card": "\u8d35A62411",
      "lng": 106.674057
    },
    {
      "id": 1,
      "lat": 27.122062,
      "vehicle_card": "\u8d35A59677",
      "lng": 106.910263
    },
    {
      "id": 1,
      "lat": 26.489587,
      "vehicle_card": "\u8d35A60692",
      "lng": 106.620384
    },
    {
      "id": 1,
      "lat": 26.600749,
      "vehicle_card": "\u8d35A11L02",
      "lng": 106.655921
    },
    {
      "id": 1,
      "lat": 26.412191,
      "vehicle_card": "\u8d35A62611",
      "lng": 106.66751
    },
    {
      "id": 1,
      "lat": 26.440248,
      "vehicle_card": "\u8d35A62405",
      "lng": 106.674034
    },
    {
      "id": 1,
      "lat": 26.405178,
      "vehicle_card": "\u8d35A60718",
      "lng": 106.672393
    },
    {
      "id": 1,
      "lat": 26.432998,
      "vehicle_card": "\u8d35A60634",
      "lng": 106.667915
    },
    {
      "id": 1,
      "lat": 26.443311,
      "vehicle_card": "\u8d35A48138",
      "lng": 106.673171
    },
    {
      "id": 1,
      "lat": 26.420438,
      "vehicle_card": "\u8d35A60698",
      "lng": 106.673255
    },
    {
      "id": 1,
      "lat": 26.429302,
      "vehicle_card": "\u8d35A56914",
      "lng": 106.673278
    },
    {
      "id": 1,
      "lat": 26.502092,
      "vehicle_card": "\u8d35A60696",
      "lng": 106.670272
    },
    {
      "id": 1,
      "lat": 26.397027,
      "vehicle_card": "\u8d35A60695",
      "lng": 106.672775
    },
    {
      "id": 1,
      "lat": 26.439767,
      "vehicle_card": "\u8d35A62613",
      "lng": 106.673713
    },
    {
      "id": 1,
      "lat": 26.471601,
      "vehicle_card": "\u8d35A86446",
      "lng": 106.555244
    },
    {
      "id": 1,
      "lat": 26.599782,
      "vehicle_card": "\u8d35AM5322",
      "lng": 106.65586
    },
    {
      "id": 1,
      "lat": 26.381942,
      "vehicle_card": "\u8d35A62962",
      "lng": 106.662864
    },
    {
      "id": 1,
      "lat": 26.362066,
      "vehicle_card": "\u8d35A62950",
      "lng": 106.680252
    },
    {
      "id": 1,
      "lat": 26.412395,
      "vehicle_card": "\u8d35A85337",
      "lng": 106.664108
    },
    {
      "id": 1,
      "lat": 26.439939,
      "vehicle_card": "\u8d35A72579",
      "lng": 106.673927
    },
    {
      "id": 1,
      "lat": 26.440084,
      "vehicle_card": "\u8d35A67847",
      "lng": 106.673889
    },
    {
      "id": 1,
      "lat": 26.601018,
      "vehicle_card": "\u8d35A79S21",
      "lng": 106.655342
    },
    {
      "id": 1,
      "lat": 26.435417,
      "vehicle_card": "\u8d35A62952",
      "lng": 106.674156
    },
    {
      "id": 1,
      "lat": 26.60065,
      "vehicle_card": "\u8d35A77123",
      "lng": 106.655548
    },
    {
      "id": 1,
      "lat": 27.09604,
      "vehicle_card": "\u8d35A81473",
      "lng": 106.741432
    },
    {
      "id": 1,
      "lat": 26.714952,
      "vehicle_card": "\u8d35A67791",
      "lng": 106.62535
    },
    {
      "id": 1,
      "lat": 26.440248,
      "vehicle_card": "\u8d35A62942",
      "lng": 106.674087
    },
    {
      "id": 1,
      "lat": 26.383911,
      "vehicle_card": "\u8d35A77618",
      "lng": 106.626991
    },
    {
      "id": 1,
      "lat": 26.600763,
      "vehicle_card": "\u8d35A9375U",
      "lng": 106.656425
    },
    {
      "id": 1,
      "lat": 26.421201,
      "vehicle_card": "\u8d35A62616",
      "lng": 106.653938
    },
    {
      "id": 1,
      "lat": 26.498767,
      "vehicle_card": "\u8d35A83369",
      "lng": 106.650024
    },
    {
      "id": 1,
      "lat": 26.446857,
      "vehicle_card": "\u8d35A82975",
      "lng": 106.673225
    },
    {
      "id": 1,
      "lat": 26.440355,
      "vehicle_card": "\u8d35A62961",
      "lng": 106.673851
    },
    {
      "id": 1,
      "lat": 26.438182,
      "vehicle_card": "\u8d35A77611",
      "lng": 106.673934
    },
    {
      "id": 1,
      "lat": 26.441328,
      "vehicle_card": "\u8d35A83017",
      "lng": 106.673248
    },
    {
      "id": 1,
      "lat": 26.442302,
      "vehicle_card": "\u8d35A85330",
      "lng": 106.673355
    },
    {
      "id": 1,
      "lat": 26.364757,
      "vehicle_card": "\u8d35A62607",
      "lng": 106.681259
    },
    {
      "id": 1,
      "lat": 26.440212,
      "vehicle_card": "\u8d35A62955",
      "lng": 106.674011
    },
    {
      "id": 1,
      "lat": 27.109397,
      "vehicle_card": "\u8d35A634E9",
      "lng": 106.910758
    },
    {
      "id": 1,
      "lat": 26.949968,
      "vehicle_card": "\u8d35A9392U",
      "lng": 106.926002
    },
    {
      "id": 1,
      "lat": 27.095579,
      "vehicle_card": "\u8d35A64021",
      "lng": 106.741615
    },
    {
      "id": 1,
      "lat": 26.441114,
      "vehicle_card": "\u8d35A62956",
      "lng": 106.673301
    },
    {
      "id": 1,
      "lat": 26.397727,
      "vehicle_card": "\u8d35A62960",
      "lng": 106.672744
    },
    {
      "id": 1,
      "lat": 26.423204,
      "vehicle_card": "\u8d35A62943",
      "lng": 106.673599
    },
    {
      "id": 1,
      "lat": 26.442806,
      "vehicle_card": "\u8d35A62609",
      "lng": 106.673194
    },
    {
      "id": 1,
      "lat": 26.43086,
      "vehicle_card": "\u8d35A62949",
      "lng": 106.674186
    },
    {
      "id": 1,
      "lat": 26.618715,
      "vehicle_card": "\u8d35AT0291",
      "lng": 106.765625
    },
    {
      "id": 1,
      "lat": 26.632322,
      "vehicle_card": "\u8d35ALG177",
      "lng": 106.583221
    },
    {
      "id": 1,
      "lat": 26.439672,
      "vehicle_card": "\u8d35A87158",
      "lng": 106.669471
    },
    {
      "id": 1,
      "lat": 26.600702,
      "vehicle_card": "\u8d35AG902B",
      "lng": 106.655662
    },
    {
      "id": 1,
      "lat": 26.398668,
      "vehicle_card": "\u8d35A77580",
      "lng": 106.612861
    },
    {
      "id": 1,
      "lat": 26.440286,
      "vehicle_card": "\u8d35A62508",
      "lng": 106.673309
    },
    {
      "id": 1,
      "lat": 26.599451,
      "vehicle_card": "\u8d35A83026",
      "lng": 106.578186
    },
    {
      "id": 1,
      "lat": 26.428424,
      "vehicle_card": "\u8d35A62612",
      "lng": 106.660896
    },
    {
      "id": 1,
      "lat": 26.590017,
      "vehicle_card": "\u8d35AT1062",
      "lng": 106.740402
    },
    {
      "id": 1,
      "lat": 26.386142,
      "vehicle_card": "\u8d35A62948",
      "lng": 106.676048
    },
    {
      "id": 1,
      "lat": 26.580375,
      "vehicle_card": "\u8d35A635E2",
      "lng": 106.647407
    },
    {
      "id": 1,
      "lat": 26.483171,
      "vehicle_card": "\u8d35A83363",
      "lng": 106.632942
    },
    {
      "id": 1,
      "lat": 26.714824,
      "vehicle_card": "\u8d35A73746",
      "lng": 106.625083
    },
    {
      "id": 1,
      "lat": 26.439741,
      "vehicle_card": "\u8d35A86443",
      "lng": 106.6734
    },
    {
      "id": 1,
      "lat": 26.56287,
      "vehicle_card": "\u8d35AT1788",
      "lng": 106.694381
    },
    {
      "id": 1,
      "lat": 26.729072,
      "vehicle_card": "\u8d35AT1316",
      "lng": 106.623115
    },
    {
      "id": 1,
      "lat": 26.585697,
      "vehicle_card": "\u8d35AT1571",
      "lng": 106.549415
    },
    {
      "id": 1,
      "lat": 26.506952,
      "vehicle_card": "\u8d35AT1791",
      "lng": 106.670341
    },
    {
      "id": 1,
      "lat": 26.505702,
      "vehicle_card": "\u8d35AT1726",
      "lng": 106.670021
    },
    {
      "id": 1,
      "lat": 26.564067,
      "vehicle_card": "\u8d35AT1980",
      "lng": 106.734901
    },
    {
      "id": 1,
      "lat": 26.620122,
      "vehicle_card": "\u8d35AT1600",
      "lng": 106.70903
    },
    {
      "id": 1,
      "lat": 26.590206,
      "vehicle_card": "\u8d35AT1591",
      "lng": 106.582618
    },
    {
      "id": 1,
      "lat": 26.507566,
      "vehicle_card": "\u8d35AT1560",
      "lng": 106.670448
    },
    {
      "id": 1,
      "lat": 26.644247,
      "vehicle_card": "\u8d35AT1669",
      "lng": 106.640296
    },
    {
      "id": 1,
      "lat": 26.595462,
      "vehicle_card": "\u8d35AT2119",
      "lng": 106.660774
    },
    {
      "id": 1,
      "lat": 26.596172,
      "vehicle_card": "\u8d35AT1577",
      "lng": 106.660774
    },
    {
      "id": 1,
      "lat": 26.517496,
      "vehicle_card": "\u8d35AT1579",
      "lng": 106.672248
    },
    {
      "id": 1,
      "lat": 26.563537,
      "vehicle_card": "\u8d35AT2022",
      "lng": 106.69419
    },
    {
      "id": 1,
      "lat": 26.62878,
      "vehicle_card": "\u8d35AT1989",
      "lng": 106.763023
    },
    {
      "id": 1,
      "lat": 26.433397,
      "vehicle_card": "\u8d35A85331",
      "lng": 106.674064
    },
    {
      "id": 1,
      "lat": 26.506919,
      "vehicle_card": "\u8d35AT1797",
      "lng": 106.670089
    },
    {
      "id": 1,
      "lat": 26.570913,
      "vehicle_card": "\u8d35AT1721",
      "lng": 106.73339
    },
    {
      "id": 1,
      "lat": 26.642969,
      "vehicle_card": "\u8d35AT1803",
      "lng": 106.668403
    },
    {
      "id": 1,
      "lat": 26.592927,
      "vehicle_card": "\u8d35AT1836",
      "lng": 106.745666
    },
    {
      "id": 1,
      "lat": 26.602743,
      "vehicle_card": "\u8d35AT1072",
      "lng": 106.706588
    },
    {
      "id": 1,
      "lat": 26.556692,
      "vehicle_card": "\u8d35AT1187",
      "lng": 106.709785
    },
    {
      "id": 1,
      "lat": 26.559064,
      "vehicle_card": "\u8d35AT1307",
      "lng": 106.771774
    },
    {
      "id": 1,
      "lat": 26.600959,
      "vehicle_card": "\u8d35AZJ070",
      "lng": 106.656425
    },
    {
      "id": 1,
      "lat": 26.553386,
      "vehicle_card": "\u8d35AT1375",
      "lng": 106.681083
    },
    {
      "id": 1,
      "lat": 26.573825,
      "vehicle_card": "\u8d35AT2199",
      "lng": 106.705642
    },
    {
      "id": 1,
      "lat": 26.582372,
      "vehicle_card": "\u8d35AT1531",
      "lng": 106.649383
    },
    {
      "id": 1,
      "lat": 26.548765,
      "vehicle_card": "\u8d35AT1592",
      "lng": 106.795516
    },
    {
      "id": 1,
      "lat": 26.589683,
      "vehicle_card": "\u8d35AT2016",
      "lng": 106.737182
    },
    {
      "id": 1,
      "lat": 26.56954,
      "vehicle_card": "\u8d35AT2018",
      "lng": 106.698646
    },
    {
      "id": 1,
      "lat": 26.592586,
      "vehicle_card": "\u8d35AT1463",
      "lng": 106.703178
    },
    {
      "id": 1,
      "lat": 27.011562,
      "vehicle_card": "\u8d35A55513",
      "lng": 107.089431
    },
    {
      "id": 1,
      "lat": 26.473938,
      "vehicle_card": "\u8d35A65267",
      "lng": 106.745188
    },
    {
      "id": 1,
      "lat": 26.483127,
      "vehicle_card": "\u8d35AA0899",
      "lng": 106.735779
    },
    {
      "id": 1,
      "lat": 26.775413,
      "vehicle_card": "\u8d35A51385",
      "lng": 106.746758
    },
    {
      "id": 1,
      "lat": 26.897021,
      "vehicle_card": "\u8d35A78311",
      "lng": 106.565075
    },
    {
      "id": 1,
      "lat": 26.507524,
      "vehicle_card": "\u8d35AT1420",
      "lng": 106.698403
    },
    {
      "id": 1,
      "lat": 26.66273,
      "vehicle_card": "\u8d35A65456",
      "lng": 106.652075
    },
    {
      "id": 1,
      "lat": 26.3949,
      "vehicle_card": "\u8d35A53030",
      "lng": 106.670324
    },
    {
      "id": 1,
      "lat": 26.685108,
      "vehicle_card": "\u8d35A82565",
      "lng": 106.681964
    },
    {
      "id": 1,
      "lat": 26.56551,
      "vehicle_card": "\u8d35AU9838",
      "lng": 106.465008
    },
    {
      "id": 1,
      "lat": 27.04411,
      "vehicle_card": "\u8d35AA7438",
      "lng": 106.735095
    },
    {
      "id": 1,
      "lat": 26.451128,
      "vehicle_card": "\u8d35A37863",
      "lng": 106.738891
    },
    {
      "id": 1,
      "lat": 26.537156,
      "vehicle_card": "\u8d35AT1793",
      "lng": 106.788668
    },
    {
      "id": 1,
      "lat": 26.775299,
      "vehicle_card": "\u8d35A82767",
      "lng": 106.748178
    },
    {
      "id": 1,
      "lat": 26.632102,
      "vehicle_card": "\u8d35AU6308",
      "lng": 106.584437
    },
    {
      "id": 1,
      "lat": 26.408184,
      "vehicle_card": "\u8d35A41087",
      "lng": 106.666976
    },
    {
      "id": 1,
      "lat": 26.63016,
      "vehicle_card": "\u8d35AT2255",
      "lng": 106.75472
    },
    {
      "id": 1,
      "lat": 26.838912,
      "vehicle_card": "\u8d35AU4185",
      "lng": 106.595013
    },
    {
      "id": 1,
      "lat": 26.450895,
      "vehicle_card": "\u8d35A32234",
      "lng": 106.738716
    },
    {
      "id": 1,
      "lat": 27.056442,
      "vehicle_card": "\u8d35AUB218",
      "lng": 106.981316
    },
    {
      "id": 1,
      "lat": 26.561277,
      "vehicle_card": "\u8d35AT0959",
      "lng": 106.723953
    },
    {
      "id": 1,
      "lat": 26.697999,
      "vehicle_card": "\u8d35AU4175",
      "lng": 106.620644
    },
    {
      "id": 1,
      "lat": 26.941391,
      "vehicle_card": "\u8d35A78259",
      "lng": 106.52166
    },
    {
      "id": 1,
      "lat": 26.648866,
      "vehicle_card": "\u8d35AU5328",
      "lng": 106.795873
    },
    {
      "id": 1,
      "lat": 27.051294,
      "vehicle_card": "\u8d35AU9117",
      "lng": 106.988632
    },
    {
      "id": 1,
      "lat": 27.045951,
      "vehicle_card": "\u8d35AU9112",
      "lng": 106.968883
    },
    {
      "id": 1,
      "lat": 26.5905,
      "vehicle_card": "\u8d35A46878",
      "lng": 106.792978
    },
    {
      "id": 1,
      "lat": 26.659426,
      "vehicle_card": "\u8d35A32164",
      "lng": 106.703718
    },
    {
      "id": 1,
      "lat": 26.596939,
      "vehicle_card": "\u8d35A01612",
      "lng": 106.577674
    },
    {
      "id": 1,
      "lat": 26.703593,
      "vehicle_card": "\u8d35A47353",
      "lng": 106.688406
    },
    {
      "id": 1,
      "lat": 26.478473,
      "vehicle_card": "\u8d35A86803",
      "lng": 106.546945
    },
    {
      "id": 1,
      "lat": 26.553873,
      "vehicle_card": "\u8d35AU9382",
      "lng": 106.452411
    },
    {
      "id": 1,
      "lat": 26.700295,
      "vehicle_card": "\u8d35A5874C",
      "lng": 106.652054
    },
    {
      "id": 1,
      "lat": 26.459712,
      "vehicle_card": "\u8d35A49612",
      "lng": 106.73476
    },
    {
      "id": 1,
      "lat": 26.971466,
      "vehicle_card": "\u8d35A43302",
      "lng": 107.143586
    },
    {
      "id": 1,
      "lat": 26.57591,
      "vehicle_card": "\u8d35A64868",
      "lng": 106.493992
    },
    {
      "id": 1,
      "lat": 26.935914,
      "vehicle_card": "\u8d35A71284",
      "lng": 106.696288
    },
    {
      "id": 1,
      "lat": 26.536736,
      "vehicle_card": "\u8d35AT1855",
      "lng": 106.788073
    },
    {
      "id": 1,
      "lat": 26.838378,
      "vehicle_card": "\u8d35AU4182",
      "lng": 106.594978
    },
    {
      "id": 1,
      "lat": 27.075301,
      "vehicle_card": "\u8d35A503J7",
      "lng": 106.98338
    },
    {
      "id": 1,
      "lat": 26.933615,
      "vehicle_card": "\u8d35A46918",
      "lng": 106.456854
    },
    {
      "id": 1,
      "lat": 26.636796,
      "vehicle_card": "\u8d35AU4825",
      "lng": 106.768644
    },
    {
      "id": 1,
      "lat": 26.581531,
      "vehicle_card": "\u8d35A78346",
      "lng": 106.500406
    },
    {
      "id": 1,
      "lat": 26.905773,
      "vehicle_card": "\u8d35A81384",
      "lng": 106.695936
    },
    {
      "id": 1,
      "lat": 26.705837,
      "vehicle_card": "\u8d35A60683",
      "lng": 106.647026
    },
    {
      "id": 1,
      "lat": 26.990188,
      "vehicle_card": "\u8d35A54864",
      "lng": 106.941565
    },
    {
      "id": 1,
      "lat": 26.53646,
      "vehicle_card": "\u8d35AU4848",
      "lng": 106.68016
    },
    {
      "id": 1,
      "lat": 27.087106,
      "vehicle_card": "\u8d35A41082",
      "lng": 106.98924
    },
    {
      "id": 1,
      "lat": 26.610372,
      "vehicle_card": "\u8d35AU4940",
      "lng": 106.616744
    },
    {
      "id": 1,
      "lat": 27.045665,
      "vehicle_card": "\u8d35AUB096",
      "lng": 106.972063
    },
    {
      "id": 1,
      "lat": 27.045424,
      "vehicle_card": "\u8d35A530B3",
      "lng": 106.732483
    },
    {
      "id": 1,
      "lat": 26.65136,
      "vehicle_card": "\u8d35AU3990",
      "lng": 106.777194
    },
    {
      "id": 1,
      "lat": 26.542205,
      "vehicle_card": "\u8d35A50709",
      "lng": 106.78808
    },
    {
      "id": 1,
      "lat": 26.639466,
      "vehicle_card": "\u8d35A75371",
      "lng": 106.5642
    },
    {
      "id": 1,
      "lat": 27.026961,
      "vehicle_card": "\u8d35A3029C",
      "lng": 106.819733
    },
    {
      "id": 1,
      "lat": 27.091915,
      "vehicle_card": "\u8d35A68931",
      "lng": 106.741835
    },
    {
      "id": 1,
      "lat": 26.642955,
      "vehicle_card": "\u8d35AT2086",
      "lng": 106.668557
    },
    {
      "id": 1,
      "lat": 27.073783,
      "vehicle_card": "\u8d35AA1837",
      "lng": 106.991797
    },
    {
      "id": 1,
      "lat": 26.677398,
      "vehicle_card": "\u8d35A43970",
      "lng": 106.737195
    },
    {
      "id": 1,
      "lat": 26.514346,
      "vehicle_card": "\u8d35A74415",
      "lng": 106.749344
    },
    {
      "id": 1,
      "lat": 26.470491,
      "vehicle_card": "\u8d35A74435",
      "lng": 106.737907
    },
    {
      "id": 1,
      "lat": 26.567426,
      "vehicle_card": "\u8d35A43990",
      "lng": 106.75151
    },
    {
      "id": 1,
      "lat": 26.591521,
      "vehicle_card": "\u8d35A61591",
      "lng": 106.694203
    },
    {
      "id": 1,
      "lat": 26.524919,
      "vehicle_card": "\u8d35A89747",
      "lng": 106.772819
    },
    {
      "id": 1,
      "lat": 26.851259,
      "vehicle_card": "\u8d35AU4163",
      "lng": 106.715156
    },
    {
      "id": 1,
      "lat": 27.079101,
      "vehicle_card": "\u8d35A87319",
      "lng": 106.743797
    },
    {
      "id": 1,
      "lat": 27.080375,
      "vehicle_card": "\u8d35A24933",
      "lng": 106.900924
    },
    {
      "id": 1,
      "lat": 26.609715,
      "vehicle_card": "\u8d35A83411",
      "lng": 106.574833
    },
    {
      "id": 1,
      "lat": 26.596406,
      "vehicle_card": "\u8d35A87432",
      "lng": 106.57701
    },
    {
      "id": 1,
      "lat": 26.995726,
      "vehicle_card": "\u8d35A57714",
      "lng": 106.807603
    },
    {
      "id": 1,
      "lat": 27.097825,
      "vehicle_card": "\u8d35A87271",
      "lng": 106.706355
    },
    {
      "id": 1,
      "lat": 27.097036,
      "vehicle_card": "\u8d35A42639",
      "lng": 106.909048
    },
    {
      "id": 1,
      "lat": 26.747503,
      "vehicle_card": "\u8d35A61228",
      "lng": 106.845096
    },
    {
      "id": 1,
      "lat": 26.598558,
      "vehicle_card": "\u8d35A29399",
      "lng": 106.576746
    },
    {
      "id": 1,
      "lat": 26.598481,
      "vehicle_card": "\u8d35AA1900",
      "lng": 106.576031
    },
    {
      "id": 1,
      "lat": 26.606693,
      "vehicle_card": "\u8d35A54883",
      "lng": 106.720245
    },
    {
      "id": 1,
      "lat": 26.583326,
      "vehicle_card": "\u8d35A49155",
      "lng": 106.664688
    },
    {
      "id": 1,
      "lat": 26.598463,
      "vehicle_card": "\u8d35A78263",
      "lng": 106.576652
    },
    {
      "id": 1,
      "lat": 26.59896,
      "vehicle_card": "\u8d35A78073",
      "lng": 106.577224
    },
    {
      "id": 1,
      "lat": 26.59934,
      "vehicle_card": "\u8d35A80658",
      "lng": 106.574821
    },
    {
      "id": 1,
      "lat": 26.583332,
      "vehicle_card": "\u8d35A49151",
      "lng": 106.664657
    },
    {
      "id": 1,
      "lat": 26.533828,
      "vehicle_card": "\u8d35AT2033",
      "lng": 106.782363
    },
    {
      "id": 1,
      "lat": 27.068021,
      "vehicle_card": "\u8d35A55373",
      "lng": 106.96436
    },
    {
      "id": 1,
      "lat": 26.847675,
      "vehicle_card": "\u8d35A78090",
      "lng": 106.92573
    },
    {
      "id": 1,
      "lat": 26.760413,
      "vehicle_card": "\u8d35A37875",
      "lng": 106.690236
    },
    {
      "id": 1,
      "lat": 27.034798,
      "vehicle_card": "\u8d35A01483",
      "lng": 106.955606
    },
    {
      "id": 1,
      "lat": 27.162383,
      "vehicle_card": "\u8d35A36353",
      "lng": 106.724948
    },
    {
      "id": 1,
      "lat": 26.63622,
      "vehicle_card": "\u8d35A47093",
      "lng": 106.579281
    },
    {
      "id": 1,
      "lat": 27.015456,
      "vehicle_card": "\u8d35A60735",
      "lng": 106.718191
    },
    {
      "id": 1,
      "lat": 26.598771,
      "vehicle_card": "\u8d35A51103",
      "lng": 106.576346
    },
    {
      "id": 1,
      "lat": 26.597266,
      "vehicle_card": "\u8d35A51098",
      "lng": 106.575778
    },
    {
      "id": 1,
      "lat": 27.066892,
      "vehicle_card": "\u8d35A65063",
      "lng": 106.964912
    },
    {
      "id": 1,
      "lat": 26.598175,
      "vehicle_card": "\u8d35A24809",
      "lng": 106.575836
    },
    {
      "id": 1,
      "lat": 26.598108,
      "vehicle_card": "\u8d35A77747",
      "lng": 106.575866
    },
    {
      "id": 1,
      "lat": 26.525436,
      "vehicle_card": "\u8d35A68611",
      "lng": 106.772913
    },
    {
      "id": 1,
      "lat": 27.171308,
      "vehicle_card": "\u8d35AA4576",
      "lng": 106.722355
    },
    {
      "id": 1,
      "lat": 27.066066,
      "vehicle_card": "\u8d35A54840",
      "lng": 106.96479
    },
    {
      "id": 1,
      "lat": 27.066032,
      "vehicle_card": "\u8d35A54880",
      "lng": 106.96479
    },
    {
      "id": 1,
      "lat": 26.597723,
      "vehicle_card": "\u8d35A01529",
      "lng": 106.577003
    },
    {
      "id": 1,
      "lat": 27.046468,
      "vehicle_card": "\u8d35A87372",
      "lng": 106.581466
    },
    {
      "id": 1,
      "lat": 26.599353,
      "vehicle_card": "\u8d35A43395",
      "lng": 106.575508
    },
    {
      "id": 1,
      "lat": 26.82098,
      "vehicle_card": "\u8d35A89798",
      "lng": 106.707165
    },
    {
      "id": 1,
      "lat": 26.741721,
      "vehicle_card": "\u8d35A81518",
      "lng": 106.839415
    },
    {
      "id": 1,
      "lat": 26.59624,
      "vehicle_card": "\u8d35AU4799",
      "lng": 106.653391
    },
    {
      "id": 1,
      "lat": 27.147741,
      "vehicle_card": "\u8d35A89820",
      "lng": 106.724041
    },
    {
      "id": 1,
      "lat": 26.521768,
      "vehicle_card": "\u8d35AU4917",
      "lng": 106.697716
    },
    {
      "id": 1,
      "lat": 27.07945,
      "vehicle_card": "\u8d35A46888",
      "lng": 106.741795
    },
    {
      "id": 1,
      "lat": 26.5987,
      "vehicle_card": "\u8d35A32266",
      "lng": 106.575966
    },
    {
      "id": 1,
      "lat": 26.596558,
      "vehicle_card": "\u8d35A87425",
      "lng": 106.57686
    },
    {
      "id": 1,
      "lat": 26.886301,
      "vehicle_card": "\u8d35A49562",
      "lng": 106.9383
    },
    {
      "id": 1,
      "lat": 26.524232,
      "vehicle_card": "\u8d35A61292",
      "lng": 106.772102
    },
    {
      "id": 1,
      "lat": 26.598247,
      "vehicle_card": "\u8d35A01276",
      "lng": 106.57637
    },
    {
      "id": 1,
      "lat": 26.597955,
      "vehicle_card": "\u8d35A52127",
      "lng": 106.575759
    },
    {
      "id": 1,
      "lat": 26.598585,
      "vehicle_card": "\u8d35A81568",
      "lng": 106.576171
    },
    {
      "id": 1,
      "lat": 26.524587,
      "vehicle_card": "\u8d35A22663",
      "lng": 106.772018
    },
    {
      "id": 1,
      "lat": 26.598564,
      "vehicle_card": "\u8d35AA9599",
      "lng": 106.57637
    },
    {
      "id": 1,
      "lat": 27.066131,
      "vehicle_card": "\u8d35AUA763",
      "lng": 106.949325
    },
    {
      "id": 1,
      "lat": 26.598482,
      "vehicle_card": "\u8d35A01296",
      "lng": 106.577201
    },
    {
      "id": 1,
      "lat": 27.047046,
      "vehicle_card": "\u8d35A87282",
      "lng": 106.58068
    },
    {
      "id": 1,
      "lat": 26.59876,
      "vehicle_card": "\u8d35A72359",
      "lng": 106.57656
    },
    {
      "id": 1,
      "lat": 26.598831,
      "vehicle_card": "\u8d35A01339",
      "lng": 106.576776
    },
    {
      "id": 1,
      "lat": 26.658301,
      "vehicle_card": "\u8d35A55227",
      "lng": 106.937348
    },
    {
      "id": 1,
      "lat": 26.623391,
      "vehicle_card": "\u8d35AX4553",
      "lng": 106.619253
    },
    {
      "id": 1,
      "lat": 26.412131,
      "vehicle_card": "\u8d35AU6889",
      "lng": 106.668823
    },
    {
      "id": 1,
      "lat": 27.06774,
      "vehicle_card": "\u8d35AU9101",
      "lng": 106.967203
    },
    {
      "id": 1,
      "lat": 26.598731,
      "vehicle_card": "\u8d35A21476",
      "lng": 106.575948
    },
    {
      "id": 1,
      "lat": 26.734446,
      "vehicle_card": "\u8d35A52359",
      "lng": 106.6911
    },
    {
      "id": 1,
      "lat": 26.964143,
      "vehicle_card": "\u8d35A48157",
      "lng": 106.510891
    },
    {
      "id": 1,
      "lat": 26.936041,
      "vehicle_card": "\u8d35A22463",
      "lng": 106.696108
    },
    {
      "id": 1,
      "lat": 26.585905,
      "vehicle_card": "\u8d35AT2068",
      "lng": 106.655175
    },
    {
      "id": 1,
      "lat": 27.126528,
      "vehicle_card": "\u8d35A83423",
      "lng": 106.5646
    },
    {
      "id": 1,
      "lat": 27.10384,
      "vehicle_card": "\u8d35A81084",
      "lng": 106.706738
    },
    {
      "id": 1,
      "lat": 26.602466,
      "vehicle_card": "\u8d35A58328",
      "lng": 106.623754
    },
    {
      "id": 1,
      "lat": 26.586643,
      "vehicle_card": "\u8d35AT0663",
      "lng": 106.735645
    },
    {
      "id": 1,
      "lat": 26.545924,
      "vehicle_card": "\u8d35A406D4",
      "lng": 106.482418
    },
    {
      "id": 1,
      "lat": 26.935941,
      "vehicle_card": "\u8d35A58392",
      "lng": 106.696238
    },
    {
      "id": 1,
      "lat": 26.628408,
      "vehicle_card": "\u8d35A63908",
      "lng": 106.361583
    }
    ],
    "type": "taxi"
}